{"lastUpdated":"2026-06-16T23:53:34.324Z","seriesId":208564,"title":"カードファイト!! ヴァンガード レギオンメイト編","thumbnailUrl":"https://nicovideo.cdn.nimg.jp/thumbnails/38296937/38296937.1353699","descriptionFirst":"リンクジョーカーの侵攻を先導アイチが防いでから、世界には平和な日常が戻っていた。そんな中、カードキャピタルを訪れた櫂トシキに、思いもよらない出来事が待ち受けていた。櫂トシキによる新たな物語が今、幕を開ける\n\n櫂トシキ:佐藤拓也／石田ナオキ:奈良 徹／戸倉ミサキ:橘田いずみ／先導エミ:榎本温子／飛田マイ:大久保瑠美／新田シン:森嶋秀太／先導アイチ:代永 翼／立凪コーリン:三森すずこ\n\n製作総指揮・原案:木谷高明／原作:ブシロード/伊藤 彰／連載:月刊ブシロード／監督:辻 初樹／シリーズ構成:浦畑達彦／カードファイト構成:中村 聡（遊宝洞）／キャラクターデザイン:とみなが まり／美術監督:明石聖子／色彩設計:磯貝深雪／撮影監督:蒲原有子／編集:大竹弥生／音楽:根岸貴幸／音響監督:高寺たけし／アニメーション制作:トムス・エンタテインメント／製作:テレビ東京/創通/電通\n\n©ヴァンガードプロジェクト\n\n次話→so38297045","tags":["カード","ヴァンガード_各編第一話・劇場版リンク","レギオンメイト編","ヴァンガード163話⇆164話移動用リンク","SF/ファンタジー"],"cours":null,"colKey":"か","relatedSeries":[],"episodes":[{"contentId":"so38297019","episodeNo":1,"title":"カードファイト!! ヴァンガード レギオンメイト編　第164話　消えた先導者","viewCounter":1325,"commentCounter":71,"mylistCounter":21,"lengthSeconds":1465,"startTime":"2021-02-26T10:00:00+09:00","thumbnailUrl":"https://nicovideo.cdn.nimg.jp/thumbnails/38297019/38297019.86755483"},{"contentId":"so38297045","episodeNo":2,"title":"カードファイト!! ヴァンガード レギオンメイト編　第165話　双闘","viewCounter":677,"commentCounter":8,"mylistCounter":1,"lengthSeconds":1465,"startTime":"2021-02-26T10:00:00+09:00","thumbnailUrl":"https://nicovideo.cdn.nimg.jp/thumbnails/38297045/38297045.27561351"},{"contentId":"so38297071","episodeNo":3,"title":"カードファイト!! ヴァンガード レギオンメイト編　第166話　アイチの影","viewCounter":587,"commentCounter":18,"mylistCounter":0,"lengthSeconds":1465,"startTime":"2021-02-26T10:00:00+09:00","thumbnailUrl":"https://nicovideo.cdn.nimg.jp/thumbnails/38297071/38297071.42094553"},{"contentId":"so38297110","episodeNo":4,"title":"カードファイト!! ヴァンガード レギオンメイト編　第167話　シーク・ザ・メイト","viewCounter":614,"commentCounter":26,"mylistCounter":2,"lengthSeconds":1465,"startTime":"2021-02-26T10:00:00+09:00","thumbnailUrl":"https://nicovideo.cdn.nimg.jp/thumbnails/38297110/38297110.72904304"},{"contentId":"so38297111","episodeNo":5,"title":"カードファイト!! ヴァンガード レギオンメイト編　第168話　ナオキの拳","viewCounter":548,"commentCounter":20,"mylistCounter":0,"lengthSeconds":1465,"startTime":"2021-02-26T10:00:00+09:00","thumbnailUrl":"https://nicovideo.cdn.nimg.jp/thumbnails/38297111/38297111.46082056"},{"contentId":"so38297112","episodeNo":6,"title":"カードファイト!! ヴァンガード レギオンメイト編　第169話　青き炎のガイヤール","viewCounter":873,"commentCounter":25,"mylistCounter":2,"lengthSeconds":1465,"startTime":"2021-02-26T10:00:00+09:00","thumbnailUrl":"https://nicovideo.cdn.nimg.jp/thumbnails/38297112/38297112.23711481"},{"contentId":"so38297086","episodeNo":7,"title":"カードファイト!! ヴァンガード レギオンメイト編　第170話　鋼のネーヴ","viewCounter":457,"commentCounter":9,"mylistCounter":0,"lengthSeconds":1465,"startTime":"2021-02-26T10:00:00+09:00","thumbnailUrl":"https://nicovideo.cdn.nimg.jp/thumbnails/38297086/38297086.68869264"},{"contentId":"so38297085","episodeNo":8,"title":"カードファイト!! ヴァンガード レギオンメイト編　第171話　先導者・櫂","viewCounter":504,"commentCounter":14,"mylistCounter":0,"lengthSeconds":1465,"startTime":"2021-02-26T10:00:00+09:00","thumbnailUrl":"https://nicovideo.cdn.nimg.jp/thumbnails/38297085/38297085.21053257"},{"contentId":"so38297084","episodeNo":9,"title":"カードファイト!! ヴァンガード レギオンメイト編　第172話　グレートダイカイザー見参！","viewCounter":487,"commentCounter":53,"mylistCounter":1,"lengthSeconds":1465,"startTime":"2021-02-26T10:00:00+09:00","thumbnailUrl":"https://nicovideo.cdn.nimg.jp/thumbnails/38297084/38297084.35376178"},{"contentId":"so38297083","episodeNo":10,"title":"カードファイト!! ヴァンガード レギオンメイト編　第173話　幻影のラティ","viewCounter":494,"commentCounter":17,"mylistCounter":1,"lengthSeconds":1465,"startTime":"2021-02-26T10:00:00+09:00","thumbnailUrl":"https://nicovideo.cdn.nimg.jp/thumbnails/38297083/38297083.35077625"},{"contentId":"so38297082","episodeNo":11,"title":"カードファイト!! ヴァンガード レギオンメイト編　第174話　凍てつく氷のセラ","viewCounter":410,"commentCounter":10,"mylistCounter":0,"lengthSeconds":1465,"startTime":"2021-02-26T10:00:00+09:00","thumbnailUrl":"https://nicovideo.cdn.nimg.jp/thumbnails/38297082/38297082.57722076"},{"contentId":"so38297081","episodeNo":12,"title":"カードファイト!! ヴァンガード レギオンメイト編　第175話　レンの約束","viewCounter":551,"commentCounter":16,"mylistCounter":1,"lengthSeconds":1465,"startTime":"2021-02-26T10:00:00+09:00","thumbnailUrl":"https://nicovideo.cdn.nimg.jp/thumbnails/38297081/38297081.42662788"},{"contentId":"so38297080","episodeNo":13,"title":"カードファイト!! ヴァンガード レギオンメイト編　第176話　アイチの戻る場所","viewCounter":532,"commentCounter":11,"mylistCounter":0,"lengthSeconds":1464,"startTime":"2021-02-26T10:00:00+09:00","thumbnailUrl":"https://nicovideo.cdn.nimg.jp/thumbnails/38297080/38297080.79222384"},{"contentId":"so38297078","episodeNo":14,"title":"カードファイト!! ヴァンガード レギオンメイト編　第177話　告げられた真実","viewCounter":520,"commentCounter":13,"mylistCounter":0,"lengthSeconds":1465,"startTime":"2021-02-26T10:00:00+09:00","thumbnailUrl":"https://nicovideo.cdn.nimg.jp/thumbnails/38297078/38297078.4528880"},{"contentId":"so38297020","episodeNo":15,"title":"カードファイト!! ヴァンガード レギオンメイト編　第178話　風の待つ島","viewCounter":497,"commentCounter":14,"mylistCounter":0,"lengthSeconds":1465,"startTime":"2021-02-26T10:00:00+09:00","thumbnailUrl":"https://nicovideo.cdn.nimg.jp/thumbnails/38297020/38297020.42371038"},{"contentId":"so38297021","episodeNo":16,"title":"カードファイト!! ヴァンガード レギオンメイト編　第179話　櫂の意志","viewCounter":692,"commentCounter":21,"mylistCounter":0,"lengthSeconds":1465,"startTime":"2021-02-26T10:00:00+09:00","thumbnailUrl":"https://nicovideo.cdn.nimg.jp/thumbnails/38297021/38297021.2757148"},{"contentId":"so38297046","episodeNo":17,"title":"カードファイト!! ヴァンガード レギオンメイト編　第180話　聖域への扉","viewCounter":571,"commentCounter":10,"mylistCounter":0,"lengthSeconds":1465,"startTime":"2021-02-26T10:00:00+09:00","thumbnailUrl":"https://nicovideo.cdn.nimg.jp/thumbnails/38297046/38297046.16297453"},{"contentId":"so38297047","episodeNo":18,"title":"カードファイト!! ヴァンガード レギオンメイト編　第181話　男気爆発(おとこぎビッグバン)","viewCounter":460,"commentCounter":9,"mylistCounter":0,"lengthSeconds":1465,"startTime":"2021-02-26T10:00:00+09:00","thumbnailUrl":"https://nicovideo.cdn.nimg.jp/thumbnails/38297047/38297047.40312868"},{"contentId":"so38297048","episodeNo":19,"title":"カードファイト!! ヴァンガード レギオンメイト編　第182話　鋼の意志","viewCounter":379,"commentCounter":8,"mylistCounter":0,"lengthSeconds":1464,"startTime":"2021-02-26T10:00:00+09:00","thumbnailUrl":"https://nicovideo.cdn.nimg.jp/thumbnails/38297048/38297048.29106546"},{"contentId":"so38297077","episodeNo":20,"title":"カードファイト!! ヴァンガード レギオンメイト編　第183話　かわらないもの","viewCounter":393,"commentCounter":10,"mylistCounter":0,"lengthSeconds":1465,"startTime":"2021-02-26T10:00:00+09:00","thumbnailUrl":"https://nicovideo.cdn.nimg.jp/thumbnails/38297077/38297077.74065015"},{"contentId":"so38297076","episodeNo":21,"title":"カードファイト!! ヴァンガード レギオンメイト編　第184話　青き炎の誓い","viewCounter":581,"commentCounter":25,"mylistCounter":1,"lengthSeconds":1464,"startTime":"2021-02-26T10:00:00+09:00","thumbnailUrl":"https://nicovideo.cdn.nimg.jp/thumbnails/38297076/38297076.81618290"},{"contentId":"so38297075","episodeNo":22,"title":"カードファイト!! ヴァンガード レギオンメイト編　第185話　煉獄の炎","viewCounter":1005,"commentCounter":43,"mylistCounter":5,"lengthSeconds":1465,"startTime":"2021-02-26T10:00:00+09:00","thumbnailUrl":"https://nicovideo.cdn.nimg.jp/thumbnails/38297075/38297075.57864261"},{"contentId":"so38297074","episodeNo":23,"title":"カードファイト!! ヴァンガード レギオンメイト編　第186話　解かれた眠り","viewCounter":757,"commentCounter":20,"mylistCounter":3,"lengthSeconds":1465,"startTime":"2021-02-26T10:00:00+09:00","thumbnailUrl":"https://nicovideo.cdn.nimg.jp/thumbnails/38297074/38297074.74841631"},{"contentId":"so38296984","episodeNo":24,"title":"カードファイト!! ヴァンガード レギオンメイト編　第187話　アイチ覚醒","viewCounter":701,"commentCounter":29,"mylistCounter":1,"lengthSeconds":1464,"startTime":"2021-02-26T10:00:00+09:00","thumbnailUrl":"https://nicovideo.cdn.nimg.jp/thumbnails/38296984/38296984.93600377"},{"contentId":"so38296983","episodeNo":25,"title":"カードファイト!! ヴァンガード レギオンメイト編　第188話　冷たい野望","viewCounter":593,"commentCounter":25,"mylistCounter":1,"lengthSeconds":1465,"startTime":"2021-02-26T10:00:00+09:00","thumbnailUrl":"https://nicovideo.cdn.nimg.jp/thumbnails/38296983/38296983.75183749"},{"contentId":"so38296982","episodeNo":26,"title":"カードファイト!! ヴァンガード レギオンメイト編　第189話　復活のオメガ","viewCounter":621,"commentCounter":32,"mylistCounter":0,"lengthSeconds":1464,"startTime":"2021-02-26T10:00:00+09:00","thumbnailUrl":"https://nicovideo.cdn.nimg.jp/thumbnails/38296982/38296982.88823109"},{"contentId":"so38296981","episodeNo":27,"title":"カードファイト!! ヴァンガード レギオンメイト編　第190話　青き炎の決意","viewCounter":696,"commentCounter":29,"mylistCounter":0,"lengthSeconds":1464,"startTime":"2021-02-26T10:00:00+09:00","thumbnailUrl":"https://nicovideo.cdn.nimg.jp/thumbnails/38296981/38296981.79434390"},{"contentId":"so38296980","episodeNo":28,"title":"カードファイト!! ヴァンガード レギオンメイト編　第191話　俺たちの場所","viewCounter":788,"commentCounter":20,"mylistCounter":0,"lengthSeconds":1465,"startTime":"2021-02-26T10:00:00+09:00","thumbnailUrl":"https://nicovideo.cdn.nimg.jp/thumbnails/38296980/38296980.20616619"},{"contentId":"so38296979","episodeNo":29,"title":"カードファイト!! ヴァンガード レギオンメイト編　第192話　炎の意地","viewCounter":803,"commentCounter":10,"mylistCounter":1,"lengthSeconds":1465,"startTime":"2021-02-26T10:00:00+09:00","thumbnailUrl":"https://nicovideo.cdn.nimg.jp/thumbnails/38296979/38296979.48007142"},{"contentId":"so38296978","episodeNo":30,"title":"カードファイト!! ヴァンガード レギオンメイト編　第193話　破滅の剣","viewCounter":831,"commentCounter":14,"mylistCounter":1,"lengthSeconds":1464,"startTime":"2021-02-26T10:00:00+09:00","thumbnailUrl":"https://nicovideo.cdn.nimg.jp/thumbnails/38296978/38296978.81839813"},{"contentId":"so38296977","episodeNo":31,"title":"カードファイト!! ヴァンガード レギオンメイト編　第194話　勇気の剣","viewCounter":1179,"commentCounter":64,"mylistCounter":4,"lengthSeconds":1465,"startTime":"2021-02-26T10:00:00+09:00","thumbnailUrl":"https://nicovideo.cdn.nimg.jp/thumbnails/38296977/38296977.91944415"},{"contentId":"so38296938","episodeNo":32,"title":"カードファイト!! ヴァンガード レギオンメイト編　第195話　旅立ちの季節","viewCounter":791,"commentCounter":19,"mylistCounter":0,"lengthSeconds":1465,"startTime":"2021-02-26T10:00:00+09:00","thumbnailUrl":"https://nicovideo.cdn.nimg.jp/thumbnails/38296938/38296938.89942070"},{"contentId":"so38296937","episodeNo":33,"title":"カードファイト!! ヴァンガード レギオンメイト編　第196話　先導者たち","viewCounter":953,"commentCounter":40,"mylistCounter":1,"lengthSeconds":1435,"startTime":"2021-02-26T10:00:00+09:00","thumbnailUrl":"https://nicovideo.cdn.nimg.jp/thumbnails/38296937/38296937.1353699"}]}