{"lastUpdated":"2026-06-16T19:53:22.776Z","seriesId":219444,"title":"妖怪ウォッチ♪","thumbnailUrl":"https://nicovideo.cdn.nimg.jp/thumbnails/38574617/38574617.43910366","descriptionFirst":"「妖怪がいる？」ごくごくフツーの小学5年生、天野ケータと妖怪執事であるウィスパーが記念すべき初めての出会いを振り返っていると、あれっ！？ケータの腕に付いているハズの妖怪ウォッチがない！歴代の妖怪ウォッチ全てをウィスパーが修理に出していたのだ。無事に修理を終えて戻ってきたウォッチが入っている箱の中を開けてみると、そこに入っていたのは・・・／「手を洗おう」ケータが手洗い場で手を洗っているところへクマやフミちゃんがやってきた。同じく手を洗うのかと思いきや…全然洗わずに去っていく！おかしいと思ったケータが妖怪ウォッチであたりを照らすと、そこには取り憑いた人を不用心にさせてしまう妖怪“ぶようじん坊”がいた！さらには他のクラスメイトたちもあらゆる妖怪にとり憑かれて手洗い場は大混乱。こんな時は…はるか未来からの使者、妖怪“ロボニャンF型”を召喚して解決だ！　他「４コマさん～おひさしぶりズラ！～」「発表！妖怪似顔絵記者会見」「妖怪スイッチ！」「妖怪劇場～桃太郎～」\n\nケータ:戸松 遥／ウィスパー:関 智一／ジバニャン:小桜エツコ／コマさん:遠藤 綾／クマ:奈良 徹／カンチ:佐藤智恵\n\n企画原案/エグゼクティブアドバイザー:日野 晃博／原作:レベルファイブ／監督:泉保 良輔／監督補佐:北條 史也／シリーズ構成:加藤 陽一／妖怪＆キャラクターデザイン原案:長野 拓造・田中 美穂／音楽:西郷憲一郎／音響監督:千葉 繁／アニメーション制作:オー・エル・エム\n\n©LEVEL-5/妖怪ウォッチ♪プロジェクト・テレビ東京\n\n次話→so38608025","tags":["アニメ","第一話","子供向け","2021年春アニメ","O.L.M","アクション/バトル"],"cours":"2021-春","colKey":"や","relatedSeries":[],"episodes":[{"contentId":"so38574617","episodeNo":1,"title":"妖怪ウォッチ♪　第1話　「妖怪がいる？」／「手を洗おう」","viewCounter":1572,"startTime":"2021-04-16T12:00:00+09:00","thumbnailUrl":"https://nicovideo.cdn.nimg.jp/thumbnails/38574617/38574617.43910366"},{"contentId":"so38608025","episodeNo":2,"title":"妖怪ウォッチ♪　第2話　「悪夢のリモートパーティー」／「めざせ人気妖怪！」","viewCounter":456,"startTime":"2021-04-23T12:00:00+09:00","thumbnailUrl":"https://nicovideo.cdn.nimg.jp/thumbnails/38608025/38608025.99544090"},{"contentId":"so38649239","episodeNo":3,"title":"妖怪ウォッチ♪　第3話　「キャッシュレス！お金ナイダー！」／「ウィスパーの秘められた力」","viewCounter":698,"startTime":"2021-04-30T12:00:00+09:00","thumbnailUrl":"https://nicovideo.cdn.nimg.jp/thumbnails/38649239/38649239.51839216"},{"contentId":"so38660349","episodeNo":4,"title":"妖怪ウォッチ♪　第4話　「スーパー妖チューバー ケータ！」／「コマさんの１００万円生活」","viewCounter":570,"startTime":"2021-05-07T12:00:00+09:00","thumbnailUrl":"https://nicovideo.cdn.nimg.jp/thumbnails/38660349/38660349.51362320"},{"contentId":"so38729166","episodeNo":5,"title":"妖怪ウォッチ♪　第5話　「負けられないクレーンゲーム」／「乙女（デバミ）のアイドル道」","viewCounter":466,"startTime":"2021-05-14T12:00:00+09:00","thumbnailUrl":"https://nicovideo.cdn.nimg.jp/thumbnails/38729166/38729166.27908212"},{"contentId":"so38753969","episodeNo":6,"title":"妖怪ウォッチ♪　第6話　「ねり消し大ブーム！」／「地獄のどんよりエレベーター」","viewCounter":414,"startTime":"2021-05-21T12:00:00+09:00","thumbnailUrl":"https://nicovideo.cdn.nimg.jp/thumbnails/38753969/38753969.98584934"},{"contentId":"so38792686","episodeNo":7,"title":"妖怪ウォッチ♪　第7話　「爆誕！最強おならユニット！」／「夢の妖怪パッドエアー！」","viewCounter":469,"startTime":"2021-05-28T12:00:00+09:00","thumbnailUrl":"https://nicovideo.cdn.nimg.jp/thumbnails/38792686/38792686.93230406"},{"contentId":"so38826374","episodeNo":8,"title":"妖怪ウォッチ♪　第8話　「ママって呼んで！」／「母熊たずねて三千里クマ！」","viewCounter":411,"startTime":"2021-06-04T12:00:00+09:00","thumbnailUrl":"https://nicovideo.cdn.nimg.jp/thumbnails/38826374/38826374.67340165"},{"contentId":"so38859816","episodeNo":9,"title":"妖怪ウォッチ♪　第9話　「マンガを止めるな！」／「妖怪クッキングスタジアム」","viewCounter":433,"startTime":"2021-06-11T12:00:00+09:00","thumbnailUrl":"https://nicovideo.cdn.nimg.jp/thumbnails/38859816/38859816.84465618"},{"contentId":"so38892839","episodeNo":10,"title":"妖怪ウォッチ♪　第10話　「あまのじゃくなケンカ」／「夢の通信回線!?　その名も１０Ｇ！」","viewCounter":434,"startTime":"2021-06-18T12:00:00+09:00","thumbnailUrl":"https://nicovideo.cdn.nimg.jp/thumbnails/38892839/38892839.82278397"},{"contentId":"so38926776","episodeNo":11,"title":"妖怪ウォッチ♪　第11話　「ハッピーバースデー！オ・レ！」／「ジバニャンのチョコボ―工場見学だニャン！」","viewCounter":395,"startTime":"2021-06-25T12:00:00+09:00","thumbnailUrl":"https://nicovideo.cdn.nimg.jp/thumbnails/38926776/38926776.31481625"},{"contentId":"so38956046","episodeNo":12,"title":"妖怪ウォッチ♪　第12話　「激闘！年に一度のチャックロワイヤル！」／「盗まれたハラマキ」","viewCounter":575,"startTime":"2021-07-02T12:00:00+09:00","thumbnailUrl":"https://nicovideo.cdn.nimg.jp/thumbnails/38956046/38956046.63053276"},{"contentId":"so38994450","episodeNo":13,"title":"妖怪ウォッチ♪　第13話　「着替えがこんがらギャル！」／「オロチ最強への道！」","viewCounter":452,"startTime":"2021-07-09T12:00:00+09:00","thumbnailUrl":"https://nicovideo.cdn.nimg.jp/thumbnails/38994450/38994450.36889083"},{"contentId":"so39023908","episodeNo":14,"title":"妖怪ウォッチ♪　第14話　「楽しい時間は一瞬ボーイ」／「ブシニャンが斬る！？」","viewCounter":448,"startTime":"2021-07-16T12:00:00+09:00","thumbnailUrl":"https://nicovideo.cdn.nimg.jp/thumbnails/39023908/39023908.15071665"},{"contentId":"so39057113","episodeNo":15,"title":"妖怪ウォッチ♪　第15話　「うずらの卵と万尾獅子」／「探訪！妖怪いわくつき物件」","viewCounter":521,"startTime":"2021-07-23T12:00:00+09:00","thumbnailUrl":"https://nicovideo.cdn.nimg.jp/thumbnails/39057113/39057113.26663075"},{"contentId":"so39091421","episodeNo":16,"title":"妖怪ウォッチ♪　第16話　「調理実習はてんてこまい！」／「届け！ジバニャンの応援（エール）」","viewCounter":344,"startTime":"2021-07-30T12:00:00+09:00","thumbnailUrl":"https://nicovideo.cdn.nimg.jp/thumbnails/39091421/39091421.68032884"},{"contentId":"so39124099","episodeNo":17,"title":"妖怪ウォッチ♪　第17話　「ネガティブーンな通知表」／「ふぶキャン！」","viewCounter":799,"startTime":"2021-08-06T12:00:00+09:00","thumbnailUrl":"https://nicovideo.cdn.nimg.jp/thumbnails/39124099/39124099.35312474"},{"contentId":"so39200020","episodeNo":18,"title":"妖怪ウォッチ♪　第18話　「プライ丼がゆるさねえ！」／「キュウビのキュンキュン大作戦♪」","viewCounter":430,"startTime":"2021-08-20T12:00:00+09:00","thumbnailUrl":"https://nicovideo.cdn.nimg.jp/thumbnails/39200020/39200020.17392870"},{"contentId":"so39235471","episodeNo":19,"title":"妖怪ウォッチ♪　第19話　「かゆかゆの夏、ニッポンの夏」／「完全破壊！？ロボニャンＦ型！」","viewCounter":384,"startTime":"2021-08-27T12:00:00+09:00","thumbnailUrl":"https://nicovideo.cdn.nimg.jp/thumbnails/39235471/39235471.40256338"},{"contentId":"so39270955","episodeNo":20,"title":"妖怪ウォッチ♪　第20話　「砂夫の素直な必殺技」／「鬼から逃走中！」","viewCounter":321,"startTime":"2021-09-03T12:00:00+09:00","thumbnailUrl":"https://nicovideo.cdn.nimg.jp/thumbnails/39270955/39270955.63868366"},{"contentId":"so39303559","episodeNo":21,"title":"妖怪ウォッチ♪　第21話　「取調室（へや）と宿題と私」／「ＵＳＡピョンと学ぶ！妖怪の夏！」","viewCounter":395,"startTime":"2021-09-10T12:00:00+09:00","thumbnailUrl":"https://nicovideo.cdn.nimg.jp/thumbnails/39303559/39303559.67729683"},{"contentId":"so39341109","episodeNo":22,"title":"妖怪ウォッチ♪　第22話　「イケメン犬とイケメンライフ！」／「じんめん犬と恋の試練！」","viewCounter":333,"startTime":"2021-09-17T12:00:00+09:00","thumbnailUrl":"https://nicovideo.cdn.nimg.jp/thumbnails/39341109/39341109.87267447"},{"contentId":"so39371176","episodeNo":23,"title":"妖怪ウォッチ♪　第23話　「なんでもかんでも自慢ハッタン」／「はしれコマさん！」","viewCounter":286,"startTime":"2021-09-24T12:00:00+09:00","thumbnailUrl":"https://nicovideo.cdn.nimg.jp/thumbnails/39371176/39371176.34160299"},{"contentId":"so39409758","episodeNo":24,"title":"妖怪ウォッチ♪　第24話　「エンマ大王が来た！」／「命がけのアルバイト」","viewCounter":516,"startTime":"2021-10-01T12:00:00+09:00","thumbnailUrl":"https://nicovideo.cdn.nimg.jp/thumbnails/39409758/39409758.65210663"},{"contentId":"so39443377","episodeNo":25,"title":"妖怪ウォッチ♪　第25話　「わわわ！？わすれん帽パニック！」／「妖怪パワースポットめぐり」","viewCounter":331,"startTime":"2021-10-08T12:00:00+09:00","thumbnailUrl":"https://nicovideo.cdn.nimg.jp/thumbnails/39443377/39443377.38574881"},{"contentId":"so39477092","episodeNo":26,"title":"妖怪ウォッチ♪　第26話　「遠足は妖怪がいっぱい」／「和を極めよ！ラストブシニャン！」","viewCounter":472,"startTime":"2021-10-15T12:00:00+09:00","thumbnailUrl":"https://nicovideo.cdn.nimg.jp/thumbnails/39477092/39477092.64608249"},{"contentId":"so39506927","episodeNo":27,"title":"妖怪ウォッチ♪　第27話　「ダイエットはガマンモス！」／「遥か未来の田舎者！ロボコマが来た！」","viewCounter":298,"startTime":"2021-10-22T12:00:00+09:00","thumbnailUrl":"https://nicovideo.cdn.nimg.jp/thumbnails/39506927/39506927.59210729"},{"contentId":"so39539078","episodeNo":28,"title":"妖怪ウォッチ♪　第28話　「ざしきわらしのハッピーフィーバー！」／「ノガッパの河童道」","viewCounter":291,"startTime":"2021-10-29T12:00:00+09:00","thumbnailUrl":"https://nicovideo.cdn.nimg.jp/thumbnails/39539078/39539078.21321794"},{"contentId":"so39577089","episodeNo":29,"title":"妖怪ウォッチ♪　第29話　「ミスタームービーンの学芸会オーディション」／「緊急手術！ウィスパーをすくえ！」","viewCounter":312,"startTime":"2021-11-05T12:00:00+09:00","thumbnailUrl":"https://nicovideo.cdn.nimg.jp/thumbnails/39577089/39577089.67184040"},{"contentId":"so39603474","episodeNo":30,"title":"妖怪ウォッチ♪　第30話　「ゲ・キ・ウ・ケ！？笑ウツボ！」／「妖怪ハロウィン！トリック・オア・トリック！」","viewCounter":600,"startTime":"2021-11-12T12:00:00+09:00","thumbnailUrl":"https://nicovideo.cdn.nimg.jp/thumbnails/39603474/39603474.20549250"},{"contentId":"so39637920","episodeNo":31,"title":"妖怪ウォッチ♪　第31話　「ふわぁ～…獅子まるの眠たい武士修行」／「おれたち宝石泥棒」","viewCounter":473,"startTime":"2021-11-19T12:00:00+09:00","thumbnailUrl":"https://nicovideo.cdn.nimg.jp/thumbnails/39637920/39637920.94042876"},{"contentId":"so39668858","episodeNo":32,"title":"妖怪ウォッチ♪　第32話　「あかなめのチョコっとレロレロ!?」／「妖怪劇場特別編～熱血！妖怪ドッジボール部～」","viewCounter":418,"startTime":"2021-11-26T12:00:00+09:00","thumbnailUrl":"https://nicovideo.cdn.nimg.jp/thumbnails/39668858/39668858.12568242"},{"contentId":"so39725640","episodeNo":33,"title":"妖怪ウォッチ♪　第33話　「ツチノコ捕獲大作戦！」／「あつまれ　ようかいの島」","viewCounter":429,"startTime":"2021-12-10T12:00:00+09:00","thumbnailUrl":"https://nicovideo.cdn.nimg.jp/thumbnails/39725640/39725640.26654770"},{"contentId":"so39761070","episodeNo":34,"title":"妖怪ウォッチ♪　第34話　「そのメガネ、うらやまスィー！」／「お口の中の戦い！虫歯伯爵ＶＳ歯磨貴婦人！」","viewCounter":375,"startTime":"2021-12-17T12:00:00+09:00","thumbnailUrl":"https://nicovideo.cdn.nimg.jp/thumbnails/39761070/39761070.17113979"},{"contentId":"so39791448","episodeNo":35,"title":"妖怪ウォッチ♪　第35話　「ピントコーンＶＳリアクション大王！」／「ロボコマ リターンズ！」","viewCounter":191,"startTime":"2021-12-24T12:00:00+09:00","thumbnailUrl":"https://nicovideo.cdn.nimg.jp/thumbnails/39791448/39791448.67578581"},{"contentId":"so39816940","episodeNo":36,"title":"妖怪ウォッチ♪　第36話　「クリスマススペシャル！フユニャンと消えたプレゼントの謎」","viewCounter":336,"startTime":"2021-12-31T12:00:00+09:00","thumbnailUrl":"https://nicovideo.cdn.nimg.jp/thumbnails/39816940/39816940.58437213"},{"contentId":"so39891547","episodeNo":37,"title":"妖怪ウォッチ♪　第37話　「さいの目入道とすごろく勝負！」／「妖怪七草がゆを食べよう」","viewCounter":199,"startTime":"2022-01-14T12:00:00+09:00","thumbnailUrl":"https://nicovideo.cdn.nimg.jp/thumbnails/39891547/39891547.82129270"},{"contentId":"so39921036","episodeNo":38,"title":"妖怪ウォッチ♪　第38話　「無茶ぶりっ子トレーニング」／「りゅーくん 転職のススメ」","viewCounter":187,"startTime":"2022-01-21T12:00:00+09:00","thumbnailUrl":"https://nicovideo.cdn.nimg.jp/thumbnails/39921036/39921036.49389890"},{"contentId":"so39952262","episodeNo":39,"title":"妖怪ウォッチ♪　第39話　「肩こりってつらいの？」／「デリバリー！「ウーバー妖ツ」をはじめよう！」","viewCounter":179,"startTime":"2022-01-28T12:00:00+09:00","thumbnailUrl":"https://nicovideo.cdn.nimg.jp/thumbnails/39952262/39952262.41333986"},{"contentId":"so39985072","episodeNo":40,"title":"妖怪ウォッチ♪　第40話　「お願いお願い！一生のお願い！」／「オロチのマフラー」","viewCounter":232,"startTime":"2022-02-04T12:00:00+09:00","thumbnailUrl":"https://nicovideo.cdn.nimg.jp/thumbnails/39985072/39985072.69371038"},{"contentId":"so40014220","episodeNo":41,"title":"妖怪ウォッチ♪　第41話　「大乱闘！妖怪オンラインゲーム！」／「妖怪パッドを落としただけなのに」","viewCounter":210,"startTime":"2022-02-11T12:00:00+09:00","thumbnailUrl":"https://nicovideo.cdn.nimg.jp/thumbnails/40014220/40014220.76365700"},{"contentId":"so40054220","episodeNo":42,"title":"妖怪ウォッチ♪　第42話　「めざせ！ベスト・オブ・ボタン押しニスト！」／「エンマとコマさんふたり旅」","viewCounter":328,"startTime":"2022-02-18T12:00:00+09:00","thumbnailUrl":"https://nicovideo.cdn.nimg.jp/thumbnails/40054220/40054220.46026804"},{"contentId":"so40088887","episodeNo":43,"title":"妖怪ウォッチ♪　第43話　「ふぶき姫の妖怪雪合戦！」／「椿姫のバレンタイン」","viewCounter":510,"startTime":"2022-02-25T12:00:00+09:00","thumbnailUrl":"https://nicovideo.cdn.nimg.jp/thumbnails/40088887/40088887.57023162"},{"contentId":"so40121793","episodeNo":44,"title":"妖怪ウォッチ♪　第44話　「大爆発！？上履きの香り！」／「コマさん、孫になる」","viewCounter":200,"startTime":"2022-03-04T12:00:00+09:00","thumbnailUrl":"https://nicovideo.cdn.nimg.jp/thumbnails/40121793/40121793.62463805"},{"contentId":"so40154591","episodeNo":45,"title":"妖怪ウォッチ♪　第45話　「冬は布団で寝コロンブス！」／「がんばれ！新米ざしきわらし！」","viewCounter":213,"startTime":"2022-03-11T12:00:00+09:00","thumbnailUrl":"https://nicovideo.cdn.nimg.jp/thumbnails/40154591/40154591.62548263"},{"contentId":"so40186379","episodeNo":46,"title":"妖怪ウォッチ♪　第46話　「最強すぎる腕ずもう対決！」／「妖怪劇場特別編～超熱血！妖怪ドッジボール部～」","viewCounter":200,"startTime":"2022-03-18T12:00:00+09:00","thumbnailUrl":"https://nicovideo.cdn.nimg.jp/thumbnails/40186379/40186379.97822499"},{"contentId":"so40219112","episodeNo":47,"title":"妖怪ウォッチ♪　第47話　「ウィスパーになりたい！」／「ジバニャンの婚活ものがたり」","viewCounter":249,"startTime":"2022-03-25T12:00:00+09:00","thumbnailUrl":"https://nicovideo.cdn.nimg.jp/thumbnails/40219112/40219112.49081341"},{"contentId":"so40251739","episodeNo":48,"title":"妖怪ウォッチ♪　第48話　「習いごとがつづかな僧！」／「ジェントル面犬のマナー講座」","viewCounter":209,"startTime":"2022-04-01T12:00:00+09:00","thumbnailUrl":"https://nicovideo.cdn.nimg.jp/thumbnails/40251739/40251739.92808745"},{"contentId":"so40284721","episodeNo":49,"title":"妖怪ウォッチ♪　第49話　「エイプリルフールにだまされるな！」／「立ち上がれ！ブリー隊長！」","viewCounter":200,"startTime":"2022-04-08T12:00:00+09:00","thumbnailUrl":"https://nicovideo.cdn.nimg.jp/thumbnails/40284721/40284721.12069550"},{"contentId":"so40315240","episodeNo":50,"title":"妖怪ウォッチ♪　第50話　「花粉症をなおせ！」／「敏腕妖怪スカウトマン！ウィスパー！」","viewCounter":253,"startTime":"2022-04-15T12:00:00+09:00","thumbnailUrl":"https://nicovideo.cdn.nimg.jp/thumbnails/40315240/40315240.18021879"},{"contentId":"so40348578","episodeNo":51,"title":"妖怪ウォッチ♪　第51話　「知ったかぶりはだれのしわざ!?」／「ツチノコのハッピーサプライズ」","viewCounter":229,"startTime":"2022-04-22T12:00:00+09:00","thumbnailUrl":"https://nicovideo.cdn.nimg.jp/thumbnails/40348578/40348578.72477292"},{"contentId":"so40381780","episodeNo":52,"title":"妖怪ウォッチ♪　第52話　「命をかけた席替え！」／「ジバニャンの桜前線北上中！」","viewCounter":224,"startTime":"2022-04-29T12:00:00+09:00","thumbnailUrl":"https://nicovideo.cdn.nimg.jp/thumbnails/40381780/40381780.19856871"},{"contentId":"so40406787","episodeNo":53,"title":"妖怪ウォッチ♪　第53話　「ゼッタイ！フミちゃんと帰ろう！」／「どこ行った！？ウィスパーの大事なもの！」","viewCounter":217,"startTime":"2022-05-06T12:00:00+09:00","thumbnailUrl":"https://nicovideo.cdn.nimg.jp/thumbnails/40406787/40406787.91496999"},{"contentId":"so40454616","episodeNo":54,"title":"妖怪ウォッチ♪　第54話　「結成！夜更かし最強チーム！」／「ジバニャンのヒッチハイク奮闘記」","viewCounter":192,"startTime":"2022-05-13T12:00:00+09:00","thumbnailUrl":"https://nicovideo.cdn.nimg.jp/thumbnails/40454616/40454616.45146540"},{"contentId":"so40487649","episodeNo":55,"title":"妖怪ウォッチ♪　第55話　「史上最長！長い長い長～い戦い！」／「ブシニャン武芸帳」","viewCounter":205,"startTime":"2022-05-20T12:00:00+09:00","thumbnailUrl":"https://nicovideo.cdn.nimg.jp/thumbnails/40487649/40487649.89188638"},{"contentId":"so40522039","episodeNo":56,"title":"妖怪ウォッチ♪　第56話　「やり直し！母の日！」／「激ウマ！妖怪カレーの秘密！」","viewCounter":156,"startTime":"2022-05-27T12:00:00+09:00","thumbnailUrl":"https://nicovideo.cdn.nimg.jp/thumbnails/40522039/40522039.63833899"},{"contentId":"so40558630","episodeNo":57,"title":"妖怪ウォッチ♪　第57話　「妖怪が見えるフミちゃん!?」／「永遠のライバル!?オロチＶＳキュウビ！」","viewCounter":270,"startTime":"2022-06-03T12:00:00+09:00","thumbnailUrl":"https://nicovideo.cdn.nimg.jp/thumbnails/40558630/40558630.60189874"},{"contentId":"so40594921","episodeNo":58,"title":"妖怪ウォッチ♪　第58話　「激痛！足の小指をぶつけるな！」／「妖怪執事ナンバーワン決定戦！」","viewCounter":207,"startTime":"2022-06-10T12:00:00+09:00","thumbnailUrl":"https://nicovideo.cdn.nimg.jp/thumbnails/40594921/40594921.2206872"},{"contentId":"so40630392","episodeNo":59,"title":"妖怪ウォッチ♪　第59話　「レジでの注文！テンパるンバ！」／「恐怖!?妖怪健康診断」","viewCounter":157,"startTime":"2022-06-17T12:00:00+09:00","thumbnailUrl":"https://nicovideo.cdn.nimg.jp/thumbnails/40630392/40630392.2856684"},{"contentId":"so40664495","episodeNo":60,"title":"妖怪ウォッチ♪　第60話　「プログラミングをハッキング！」／「コマさん、ペットになる」","viewCounter":188,"startTime":"2022-06-24T12:00:00+09:00","thumbnailUrl":"https://nicovideo.cdn.nimg.jp/thumbnails/40664495/40664495.42473042"},{"contentId":"so40699029","episodeNo":61,"title":"妖怪ウォッチ♪　第61話　「突撃！焼き肉食べ放題！」／「激闘！妖怪水かけ祭り！」","viewCounter":204,"startTime":"2022-07-01T12:00:00+09:00","thumbnailUrl":"https://nicovideo.cdn.nimg.jp/thumbnails/40699029/40699029.82065296"},{"contentId":"so40699028","episodeNo":62,"title":"妖怪ウォッチ♪　第62話　「大ピンチ！閉じ込められたケータたち」／「妖怪ガールズトーク♪」","viewCounter":290,"startTime":"2022-07-01T19:00:00+09:00","thumbnailUrl":"https://nicovideo.cdn.nimg.jp/thumbnails/40699028/40699028.33664856"},{"contentId":"so40732423","episodeNo":63,"title":"妖怪ウォッチ♪　第63話　「虫取りはムシできぬ試練！」／「グッモーニン！？セミまる」","viewCounter":204,"startTime":"2022-07-08T19:00:00+09:00","thumbnailUrl":"https://nicovideo.cdn.nimg.jp/thumbnails/40732423/40732423.13433607"},{"contentId":"so40765152","episodeNo":64,"title":"妖怪ウォッチ♪　第64話　「エジソンと自由研究！」／「じんめん犬のケーキ屋さん」","viewCounter":171,"startTime":"2022-07-15T19:00:00+09:00","thumbnailUrl":"https://nicovideo.cdn.nimg.jp/thumbnails/40765152/40765152.15560409"},{"contentId":"so40798426","episodeNo":65,"title":"妖怪ウォッチ♪　第65話　「夏休み！釣れない魚釣り！」／「妖怪百物語」","viewCounter":208,"startTime":"2022-07-22T19:00:00+09:00","thumbnailUrl":"https://nicovideo.cdn.nimg.jp/thumbnails/40798426/40798426.47388125"},{"contentId":"so40829647","episodeNo":66,"title":"妖怪ウォッチ♪　第66話　「ガマンできないタイムセール！」／「妖怪女子刑務所」","viewCounter":184,"startTime":"2022-07-29T19:00:00+09:00","thumbnailUrl":"https://nicovideo.cdn.nimg.jp/thumbnails/40829647/40829647.98135372"},{"contentId":"so40869900","episodeNo":67,"title":"妖怪ウォッチ♪　第67話　「お昼ゴハン代　節約大作戦！」／「夏本番！あせっか鬼は大忙し」","viewCounter":189,"startTime":"2022-08-05T19:00:00+09:00","thumbnailUrl":"https://nicovideo.cdn.nimg.jp/thumbnails/40869900/40869900.7940804"},{"contentId":"so40900273","episodeNo":68,"title":"妖怪ウォッチ♪　第68話　「妖怪も夏休みＳＰ！コマ兄弟　実家に帰る」／「ジバニャン　海へ行く」","viewCounter":216,"startTime":"2022-08-12T19:00:00+09:00","thumbnailUrl":"https://nicovideo.cdn.nimg.jp/thumbnails/40900273/40900273.68076710"},{"contentId":"so40977275","episodeNo":69,"title":"妖怪ウォッチ♪　第69話　「奇跡！ケータ、夏休みの宿題を終わらせる」／「最速妖怪決定戦！サマーバケーションレース！」","viewCounter":198,"startTime":"2022-08-26T19:00:00+09:00","thumbnailUrl":"https://nicovideo.cdn.nimg.jp/thumbnails/40977275/40977275.21293071"},{"contentId":"so41014424","episodeNo":70,"title":"妖怪ウォッチ♪　第70話　「おとなブリたいお年頃！」／「戦え！ヘルズプリンセス！～結婚式の陰謀～」","viewCounter":222,"startTime":"2022-09-02T19:00:00+09:00","thumbnailUrl":"https://nicovideo.cdn.nimg.jp/thumbnails/41014424/41014424.97329594"},{"contentId":"so41048178","episodeNo":71,"title":"妖怪ウォッチ♪　第71話　「夏は毎日そうめん！」／「伝説のフワフワかき氷」","viewCounter":182,"startTime":"2022-09-09T19:00:00+09:00","thumbnailUrl":"https://nicovideo.cdn.nimg.jp/thumbnails/41048178/41048178.70141977"},{"contentId":"so41082503","episodeNo":72,"title":"妖怪ウォッチ♪　第72話　「あこがれのヘアスタイル」／「こんな台風あり！？妖怪台風当番！」","viewCounter":168,"startTime":"2022-09-16T19:00:00+09:00","thumbnailUrl":"https://nicovideo.cdn.nimg.jp/thumbnails/41082503/41082503.40503887"},{"contentId":"so41111647","episodeNo":73,"title":"妖怪ウォッチ♪　第73話　「衝撃の新機能！？妖怪ウォッチ零式を探せ！」","viewCounter":279,"startTime":"2022-09-23T19:00:00+09:00","thumbnailUrl":"https://nicovideo.cdn.nimg.jp/thumbnails/41111647/41111647.43441889"},{"contentId":"so41148363","episodeNo":74,"title":"妖怪ウォッチ♪　第74話　「先輩！お月見したいんですけど！」／「妖怪ルームシェア」","viewCounter":220,"startTime":"2022-09-30T19:00:00+09:00","thumbnailUrl":"https://nicovideo.cdn.nimg.jp/thumbnails/41148363/41148363.17803904"},{"contentId":"so41181899","episodeNo":75,"title":"妖怪ウォッチ♪　第75話　「合唱！くちパクにご注意！」／「全世界待望！？ウィスパー、映画に出る」","viewCounter":192,"startTime":"2022-10-07T19:00:00+09:00","thumbnailUrl":"https://nicovideo.cdn.nimg.jp/thumbnails/41181899/41181899.46559449"},{"contentId":"so41224180","episodeNo":76,"title":"妖怪ウォッチ♪　第76話　「お祭りだ！射的は真剣勝負！」／「旬のフルーツニャン狩り」","viewCounter":308,"startTime":"2022-10-14T19:00:00+09:00","thumbnailUrl":"https://nicovideo.cdn.nimg.jp/thumbnails/41224180/41224180.5902062"},{"contentId":"so41256524","episodeNo":77,"title":"妖怪ウォッチ♪　第77話　「鉛筆くるくるく〜るくる！」／「チョコボーたちの日々」","viewCounter":206,"startTime":"2022-10-21T19:00:00+09:00","thumbnailUrl":"https://nicovideo.cdn.nimg.jp/thumbnails/41256524/41256524.92858384"},{"contentId":"so41287192","episodeNo":78,"title":"妖怪ウォッチ♪　第78話　「ガチで目指せ！ベスト オブ ハロウィニスト！」／「戦え！ヘルズプリンセス！～危険なハロウィン～」","viewCounter":264,"startTime":"2022-10-28T19:00:00+09:00","thumbnailUrl":"https://nicovideo.cdn.nimg.jp/thumbnails/41287192/41287192.38315150"},{"contentId":"so41316712","episodeNo":79,"title":"妖怪ウォッチ♪　第79話　「ケータ、放送委員になる！」／「究極の妖怪サバイバルレース！ＹＯＳＵＫＥ」","viewCounter":202,"startTime":"2022-11-04T19:00:00+09:00","thumbnailUrl":"https://nicovideo.cdn.nimg.jp/thumbnails/41316712/41316712.46588343"},{"contentId":"so41352188","episodeNo":80,"title":"妖怪ウォッチ♪　第80話　「ガシャに福引き！当たりをめざせ！」／「あしたのニャー」","viewCounter":186,"startTime":"2022-11-11T19:00:00+09:00","thumbnailUrl":"https://nicovideo.cdn.nimg.jp/thumbnails/41352188/41352188.49071784"},{"contentId":"so41415092","episodeNo":81,"title":"妖怪ウォッチ♪　第81話　「自分がイヤイヤ！じこけん王！」／「奪われた焼き芋！ならず者はおならず者！」","viewCounter":209,"startTime":"2022-11-25T19:00:00+09:00","thumbnailUrl":"https://nicovideo.cdn.nimg.jp/thumbnails/41415092/41415092.62576073"},{"contentId":"so41447086","episodeNo":82,"title":"妖怪ウォッチ♪　第82話　「ニオう軍団！その名は不潔ファイブ！」／「戦え！ヘルズプリンセス！～盗まれた玉手箱～」","viewCounter":224,"startTime":"2022-12-02T19:00:00+09:00","thumbnailUrl":"https://nicovideo.cdn.nimg.jp/thumbnails/41447086/41447086.76800890"},{"contentId":"so41477058","episodeNo":83,"title":"妖怪ウォッチ♪　第83話　「静かなる学級会！誰か手ぇあげてよ！」／「妖怪再生工場～呼ばれざる妖怪たち～」","viewCounter":170,"startTime":"2022-12-09T19:00:00+09:00","thumbnailUrl":"https://nicovideo.cdn.nimg.jp/thumbnails/41477058/41477058.74417785"},{"contentId":"so41508283","episodeNo":84,"title":"妖怪ウォッチ♪　第84話　「松葉杖、めっちゃカッコいい！」／「妖怪カレンダーを作ろう！」","viewCounter":165,"startTime":"2022-12-16T19:00:00+09:00","thumbnailUrl":"https://nicovideo.cdn.nimg.jp/thumbnails/41508283/41508283.702346"},{"contentId":"so41534552","episodeNo":85,"title":"妖怪ウォッチ♪　第85話　「クイズ対決！サンタク老師とクリスマスパーティー！」／「戦え！ヘルズプリンセス！～サンタを救え～」","viewCounter":377,"startTime":"2022-12-23T19:00:00+09:00","thumbnailUrl":"https://nicovideo.cdn.nimg.jp/thumbnails/41534552/41534552.28240758"},{"contentId":"so41608777","episodeNo":86,"title":"妖怪ウォッチ♪　第86話　「お正月！今年のおモチ決定戦！」／「必ず当たる！？ＹＯみくじ！」","viewCounter":298,"startTime":"2023-01-06T19:00:00+09:00","thumbnailUrl":"https://nicovideo.cdn.nimg.jp/thumbnails/41608777/41608777.11065553"},{"contentId":"so41640222","episodeNo":87,"title":"妖怪ウォッチ♪　第87話　「ケータ、フツーに戻りたい」／「オトナは誰だ！？妖怪成人式」","viewCounter":218,"startTime":"2023-01-13T19:00:00+09:00","thumbnailUrl":"https://nicovideo.cdn.nimg.jp/thumbnails/41640222/41640222.17727217"},{"contentId":"so41671401","episodeNo":88,"title":"妖怪ウォッチ♪　第88話　「集まれ！鼻水系妖怪！」／「りゅーくんの進めドラゴンロード！」","viewCounter":150,"startTime":"2023-01-20T19:00:00+09:00","thumbnailUrl":"https://nicovideo.cdn.nimg.jp/thumbnails/41671401/41671401.55034777"},{"contentId":"so41703309","episodeNo":89,"title":"妖怪ウォッチ♪　第89話　「ビシッ！なわとびの痛みを乗り越えろ！」／「ニャンコいち武道会」","viewCounter":190,"startTime":"2023-01-27T19:00:00+09:00","thumbnailUrl":"https://nicovideo.cdn.nimg.jp/thumbnails/41703309/41703309.3287850"},{"contentId":"so41736232","episodeNo":90,"title":"妖怪ウォッチ♪　第90話　「荷物を持つのダリ～っす！」／「ワタクシがオレっちでオレっちがワタクシ！？」","viewCounter":219,"startTime":"2023-02-03T19:00:00+09:00","thumbnailUrl":"https://nicovideo.cdn.nimg.jp/thumbnails/41736232/41736232.39133104"},{"contentId":"so41769713","episodeNo":91,"title":"妖怪ウォッチ♪　第91話　「チョコバナーナのバレンタイン修行」／「戦え！ヘルズプリンセス！～チョコを狙う者たち～」","viewCounter":599,"startTime":"2023-02-10T19:00:00+09:00","thumbnailUrl":"https://nicovideo.cdn.nimg.jp/thumbnails/41769713/41769713.40082453"},{"contentId":"so41803635","episodeNo":92,"title":"妖怪ウォッチ♪　第92話　「妖怪ウォッチ♪特別編　オラとコマじろうのもんげー思い出に残ったお話 大発表スペシャルズラ！」","viewCounter":434,"startTime":"2023-02-17T19:00:00+09:00","thumbnailUrl":"https://nicovideo.cdn.nimg.jp/thumbnails/41803635/41803635.68264420"},{"contentId":"so41831564","episodeNo":93,"title":"妖怪ウォッチ♪　第93話　「お家に入りたい」／「春、まだ来ないの？」","viewCounter":232,"startTime":"2023-02-24T19:00:00+09:00","thumbnailUrl":"https://nicovideo.cdn.nimg.jp/thumbnails/41831564/41831564.5726298"},{"contentId":"so41870504","episodeNo":94,"title":"妖怪ウォッチ♪　第94話　「追い抜きたくなる通学路」／「なんかで荘の新人管理人　じんめん犬！」","viewCounter":985,"startTime":"2023-03-03T19:00:00+09:00","thumbnailUrl":"https://nicovideo.cdn.nimg.jp/thumbnails/41870504/41870504.8285240"},{"contentId":"so41902466","episodeNo":95,"title":"妖怪ウォッチ♪　第95話　「フーセンガムを膨らませたい！」／「激闘！妖怪野球大会！」","viewCounter":839,"startTime":"2023-03-10T19:00:00+09:00","thumbnailUrl":"https://nicovideo.cdn.nimg.jp/thumbnails/41902466/41902466.56807026"},{"contentId":"so41935860","episodeNo":96,"title":"妖怪ウォッチ♪　第96話　「テストの絶望！」／「エンマ大王のお付きオーディション！」","viewCounter":569,"startTime":"2023-03-17T19:00:00+09:00","thumbnailUrl":"https://nicovideo.cdn.nimg.jp/thumbnails/41935860/41935860.43129155"},{"contentId":"so41975732","episodeNo":97,"title":"妖怪ウォッチ♪　第97話　「妖怪ウォッチ♪　ジバニャンvsコマさん もんげー大決戦だニャン ～前編～」","viewCounter":1880,"startTime":"2023-03-24T19:00:00+09:00","thumbnailUrl":"https://nicovideo.cdn.nimg.jp/thumbnails/41975732/41975732.37183254"},{"contentId":"so42009726","episodeNo":98,"title":"妖怪ウォッチ♪　第98話　「妖怪ウォッチ♪　ジバニャンvsコマさん もんげー大決戦だニャン ～後編～」","viewCounter":1822,"startTime":"2023-03-31T19:00:00+09:00","thumbnailUrl":"https://nicovideo.cdn.nimg.jp/thumbnails/42009726/42009726.49075843"}]}