{"lastUpdated":"2026-06-16T12:18:21.074Z","seriesId":256518,"title":"ゲッターロボＧ","thumbnailUrl":"https://nicovideo.cdn.nimg.jp/thumbnails/39209486/39209486.71997350","descriptionFirst":"「百鬼帝国…！　恐竜帝国にかわって、新たな敵が出現したようだ」（早乙女博士）恐竜帝国が壊滅して一ヶ月、新ゲッターロボが完成した。ドラゴン号に搭乗するリョウとライガー号のハヤトは、シミュレーター訓練を開始。旧ゲッターの十倍のパワーに音を上げる。早乙女博士はポセイドン号のパイロットを、元気が知り合ったタフで豪胆な男ベンケイに依頼するが、争いを好まぬベンケイはそれを断る。\n\n流竜馬:神谷明／神隼人:山田俊司／車弁慶、ブライ大帝:八奈見乗児／早乙女ミチル:吉田理保子／早乙女博士、ジョーホー:富田耕生／早乙女元気:菊池紘子／ヒドラー元帥:緒方賢一／グラー博士:矢田耕司\n\n原作:永井豪、石川賢とダイナミックプロ／企画:勝田稔男、小田克也、別所孝治／製作担当:菅原吉郎／脚本:高久進、上原正三、田村多津夫、馬嶋満、他／演出:小湊洋市、生頼昭憲、葛西治、山口康男、他／キャラクター設計:小松原一男／作画:小松原一男、落合正宗、野田卓雄／美術:辻忠直、伊藤岩光、内川文広、他／音楽:菊池俊輔\n\n©ダイナミック企画・東映アニメーション\n\n次話→so39209609","tags":["アニメ","第一話","アクション","バトル","コメント不可","ロボット","メカ","ダイナミックプロ","ゲッターロボG"],"cours":null,"colKey":"か","relatedSeries":[{"seriesId":95971,"title":"鋼鉄神ジーグ","thumbnailUrl":"https://nicovideo.cdn.nimg.jp/thumbnails/32376664/32376664.62183310"},{"seriesId":109184,"title":"ゴッドマジンガー","thumbnailUrl":"https://nicovideo.cdn.nimg.jp/thumbnails/36393511/36393511.29511422"},{"seriesId":403069,"title":"劇場版 マジンガーZ ／ INFINITY","thumbnailUrl":"https://nicovideo.cdn.nimg.jp/thumbnails/42110634/42110634.53019156"}],"episodes":[{"contentId":"so39209593","episodeNo":1,"title":"ゲッターロボＧ　第1話　甦れゲッターロボ!!","viewCounter":4694,"startTime":"2023-02-28T10:00:00+09:00","thumbnailUrl":"https://nicovideo.cdn.nimg.jp/thumbnails/39209593/39209593.64279961"},{"contentId":"so39209609","episodeNo":2,"title":"ゲッターロボＧ　第2話　恐るべき百鬼帝国の謎","viewCounter":1145,"startTime":"2023-02-28T10:00:00+09:00","thumbnailUrl":"https://nicovideo.cdn.nimg.jp/thumbnails/39209609/39209609.285945"},{"contentId":"so39209642","episodeNo":3,"title":"ゲッターロボＧ　第3話　悪の罠！ 空飛ぶ船団","viewCounter":590,"startTime":"2023-02-28T10:00:00+09:00","thumbnailUrl":"https://nicovideo.cdn.nimg.jp/thumbnails/39209642/39209642.83660747"},{"contentId":"so39209643","episodeNo":4,"title":"ゲッターロボＧ　第4話　ベンケイ！ 涙の勝利","viewCounter":498,"startTime":"2023-02-28T10:00:00+09:00","thumbnailUrl":"https://nicovideo.cdn.nimg.jp/thumbnails/39209643/39209643.34413923"},{"contentId":"so39209644","episodeNo":5,"title":"ゲッターロボＧ　第5話　恐怖の水爆大作戦","viewCounter":439,"startTime":"2023-02-28T10:00:00+09:00","thumbnailUrl":"https://nicovideo.cdn.nimg.jp/thumbnails/39209644/39209644.13304524"},{"contentId":"so39209645","episodeNo":6,"title":"ゲッターロボＧ　第6話　夢を裂く百鬼一族","viewCounter":369,"startTime":"2023-02-28T10:00:00+09:00","thumbnailUrl":"https://nicovideo.cdn.nimg.jp/thumbnails/39209645/39209645.79485822"},{"contentId":"so39209646","episodeNo":7,"title":"ゲッターロボＧ　第7話　追跡！ 黒いジェット機","viewCounter":364,"startTime":"2023-02-28T10:00:00+09:00","thumbnailUrl":"https://nicovideo.cdn.nimg.jp/thumbnails/39209646/39209646.40758375"},{"contentId":"so39209613","episodeNo":8,"title":"ゲッターロボＧ　第8話　夜空に輝く二つ星","viewCounter":332,"startTime":"2023-02-28T10:00:00+09:00","thumbnailUrl":"https://nicovideo.cdn.nimg.jp/thumbnails/39209613/39209613.78323166"},{"contentId":"so39209612","episodeNo":9,"title":"ゲッターロボＧ　第9話　ＳＯＳ！ ゲッターロボ応答せよ","viewCounter":301,"startTime":"2023-02-28T10:00:00+09:00","thumbnailUrl":"https://nicovideo.cdn.nimg.jp/thumbnails/39209612/39209612.39484349"},{"contentId":"so39209611","episodeNo":10,"title":"ゲッターロボＧ　第10話　悪魔の島を攻撃せよ！","viewCounter":298,"startTime":"2023-02-28T10:00:00+09:00","thumbnailUrl":"https://nicovideo.cdn.nimg.jp/thumbnails/39209611/39209611.44723214"},{"contentId":"so39209610","episodeNo":11,"title":"ゲッターロボＧ　第11話　百鬼帝国！ 将軍への道","viewCounter":278,"startTime":"2023-02-28T10:00:00+09:00","thumbnailUrl":"https://nicovideo.cdn.nimg.jp/thumbnails/39209610/39209610.99040202"},{"contentId":"so39209591","episodeNo":12,"title":"ゲッターロボＧ　第12話　遙かなる荒野の決闘！","viewCounter":279,"startTime":"2023-02-28T10:00:00+09:00","thumbnailUrl":"https://nicovideo.cdn.nimg.jp/thumbnails/39209591/39209591.74183897"},{"contentId":"so39209590","episodeNo":13,"title":"ゲッターロボＧ　第13話　こうもり爆弾！ 危機一髪","viewCounter":261,"startTime":"2023-02-28T10:00:00+09:00","thumbnailUrl":"https://nicovideo.cdn.nimg.jp/thumbnails/39209590/39209590.65667383"},{"contentId":"so39209589","episodeNo":14,"title":"ゲッターロボＧ　第14話　友達は風になった","viewCounter":285,"startTime":"2023-02-28T10:00:00+09:00","thumbnailUrl":"https://nicovideo.cdn.nimg.jp/thumbnails/39209589/39209589.42441098"},{"contentId":"so39209552","episodeNo":15,"title":"ゲッターロボＧ　第15話　赤い蝶のバラード","viewCounter":279,"startTime":"2023-02-28T10:00:00+09:00","thumbnailUrl":"https://nicovideo.cdn.nimg.jp/thumbnails/39209552/39209552.64738180"},{"contentId":"so39209553","episodeNo":16,"title":"ゲッターロボＧ　第16話　死闘！ 嵐吹く男の道","viewCounter":285,"startTime":"2023-02-28T10:00:00+09:00","thumbnailUrl":"https://nicovideo.cdn.nimg.jp/thumbnails/39209553/39209553.69051261"},{"contentId":"so39209574","episodeNo":17,"title":"ゲッターロボＧ　第17話　コロよ明日に吠えろ！","viewCounter":231,"startTime":"2023-02-28T10:00:00+09:00","thumbnailUrl":"https://nicovideo.cdn.nimg.jp/thumbnails/39209574/39209574.37322259"},{"contentId":"so39209575","episodeNo":18,"title":"ゲッターロボＧ　第18話　危うし伊豆半島沖！","viewCounter":252,"startTime":"2023-02-28T10:00:00+09:00","thumbnailUrl":"https://nicovideo.cdn.nimg.jp/thumbnails/39209575/39209575.64450668"},{"contentId":"so39209576","episodeNo":19,"title":"ゲッターロボＧ　第19話　早乙女博士を救出せよ！","viewCounter":222,"startTime":"2023-02-28T10:00:00+09:00","thumbnailUrl":"https://nicovideo.cdn.nimg.jp/thumbnails/39209576/39209576.83139484"},{"contentId":"so39209578","episodeNo":20,"title":"ゲッターロボＧ　第20話　大攻撃！ メカ要塞鬼","viewCounter":279,"startTime":"2023-02-28T10:00:00+09:00","thumbnailUrl":"https://nicovideo.cdn.nimg.jp/thumbnails/39209578/39209578.99947333"},{"contentId":"so39209579","episodeNo":21,"title":"ゲッターロボＧ　第21話　大決戦！ シャインスパーク","viewCounter":419,"startTime":"2023-02-28T10:00:00+09:00","thumbnailUrl":"https://nicovideo.cdn.nimg.jp/thumbnails/39209579/39209579.19745432"},{"contentId":"so39209580","episodeNo":22,"title":"ゲッターロボＧ　第22話　海底に消えたジャンボ機","viewCounter":236,"startTime":"2023-02-28T10:00:00+09:00","thumbnailUrl":"https://nicovideo.cdn.nimg.jp/thumbnails/39209580/39209580.5983870"},{"contentId":"so39209581","episodeNo":23,"title":"ゲッターロボＧ　第23話　月光に踊るピエロ","viewCounter":218,"startTime":"2023-02-28T10:00:00+09:00","thumbnailUrl":"https://nicovideo.cdn.nimg.jp/thumbnails/39209581/39209581.50222088"},{"contentId":"so39209582","episodeNo":24,"title":"ゲッターロボＧ　第24話　海に叫ぶ少年！","viewCounter":217,"startTime":"2023-02-28T10:00:00+09:00","thumbnailUrl":"https://nicovideo.cdn.nimg.jp/thumbnails/39209582/39209582.64988239"},{"contentId":"so39209583","episodeNo":25,"title":"ゲッターロボＧ　第25話　湖に消えたミチル","viewCounter":211,"startTime":"2023-02-28T10:00:00+09:00","thumbnailUrl":"https://nicovideo.cdn.nimg.jp/thumbnails/39209583/39209583.55238105"},{"contentId":"so39209585","episodeNo":26,"title":"ゲッターロボＧ　第26話　鬼になったあいつ！","viewCounter":310,"startTime":"2023-02-28T10:00:00+09:00","thumbnailUrl":"https://nicovideo.cdn.nimg.jp/thumbnails/39209585/39209585.70271702"},{"contentId":"so39209497","episodeNo":27,"title":"ゲッターロボＧ　第27話　ツバメよ元気に飛べ！","viewCounter":199,"startTime":"2023-02-28T10:00:00+09:00","thumbnailUrl":"https://nicovideo.cdn.nimg.jp/thumbnails/39209497/39209497.38495133"},{"contentId":"so39209496","episodeNo":28,"title":"ゲッターロボＧ　第28話　緑の地球が死ぬ！","viewCounter":207,"startTime":"2023-02-28T10:00:00+09:00","thumbnailUrl":"https://nicovideo.cdn.nimg.jp/thumbnails/39209496/39209496.90318692"},{"contentId":"so39209495","episodeNo":29,"title":"ゲッターロボＧ　第29話　涙のあとに口笛を","viewCounter":196,"startTime":"2023-02-28T10:00:00+09:00","thumbnailUrl":"https://nicovideo.cdn.nimg.jp/thumbnails/39209495/39209495.81779394"},{"contentId":"so39209494","episodeNo":30,"title":"ゲッターロボＧ　第30話　ドライスノー奇襲作戦！","viewCounter":200,"startTime":"2023-02-28T10:00:00+09:00","thumbnailUrl":"https://nicovideo.cdn.nimg.jp/thumbnails/39209494/39209494.14793547"},{"contentId":"so39209493","episodeNo":31,"title":"ゲッターロボＧ　第31話　燃えろ！ リョウの剣","viewCounter":205,"startTime":"2023-02-28T10:00:00+09:00","thumbnailUrl":"https://nicovideo.cdn.nimg.jp/thumbnails/39209493/39209493.45711169"},{"contentId":"so39209492","episodeNo":32,"title":"ゲッターロボＧ　第32話　元気あの子ってなんなのさ！","viewCounter":188,"startTime":"2023-02-28T10:00:00+09:00","thumbnailUrl":"https://nicovideo.cdn.nimg.jp/thumbnails/39209492/39209492.31209674"},{"contentId":"so39209491","episodeNo":33,"title":"ゲッターロボＧ　第33話　夕焼け空が知っている","viewCounter":196,"startTime":"2023-02-28T10:00:00+09:00","thumbnailUrl":"https://nicovideo.cdn.nimg.jp/thumbnails/39209491/39209491.38577122"},{"contentId":"so39209489","episodeNo":34,"title":"ゲッターロボＧ　第34話　対決！ 百鬼三兄弟","viewCounter":199,"startTime":"2023-02-28T10:00:00+09:00","thumbnailUrl":"https://nicovideo.cdn.nimg.jp/thumbnails/39209489/39209489.27491944"},{"contentId":"so39209488","episodeNo":35,"title":"ゲッターロボＧ　第35話　百鬼老兵は死なず","viewCounter":197,"startTime":"2023-02-28T10:00:00+09:00","thumbnailUrl":"https://nicovideo.cdn.nimg.jp/thumbnails/39209488/39209488.89909350"},{"contentId":"so39209487","episodeNo":36,"title":"ゲッターロボＧ　第36話　ベンケイ暗殺計画","viewCounter":201,"startTime":"2023-02-28T10:00:00+09:00","thumbnailUrl":"https://nicovideo.cdn.nimg.jp/thumbnails/39209487/39209487.12611243"},{"contentId":"so39209486","episodeNo":37,"title":"ゲッターロボＧ　第37話　危機迫る日本近海！","viewCounter":252,"startTime":"2023-02-28T10:00:00+09:00","thumbnailUrl":"https://nicovideo.cdn.nimg.jp/thumbnails/39209486/39209486.71997350"},{"contentId":"so39209498","episodeNo":38,"title":"ゲッターロボＧ　第38話　ブライ大帝決死の大反撃！","viewCounter":308,"startTime":"2023-02-28T10:00:00+09:00","thumbnailUrl":"https://nicovideo.cdn.nimg.jp/thumbnails/39209498/39209498.80572075"},{"contentId":"so39209499","episodeNo":39,"title":"ゲッターロボＧ　第39話　大決戦！ 日本上空","viewCounter":665,"startTime":"2023-02-28T10:00:00+09:00","thumbnailUrl":"https://nicovideo.cdn.nimg.jp/thumbnails/39209499/39209499.64991079"}]}