{"lastUpdated":"2026-06-16T11:29:12.521Z","seriesId":290421,"title":"賢者の弟子を名乗る賢者","thumbnailUrl":null,"descriptionFirst":"無限の可能性が広がるVRMMO『アーク・アースオンライン』で、召喚術を究めたプレイヤー・ダンブルフ。彼は仲間と建国したアルカイト王国の最高位「九賢者」として目覚ましい活躍を見せていた。この日も国王の臣下としてのロールプレイを楽しみながら、魔物討伐のクエストに挑むのだが……。ゲーム内に大きな異変が起こる。\n\nミラ:大森日雅／マリアナ:堀江由衣／ソロモン:村瀬歩／ルミナリア:日向未南／クレオス:蒼井翔太／アマラッテ:佐倉綾音／ダンブルフ:ささきいさお\n\n原作:りゅうせんひろつぐ（GCノベルズ『賢者の弟子を名乗る賢者』/マイクロマガジン社刊）／原作イラスト:藤ちょこ／監督:元永慶太郎／シリーズ構成:鴻野貴光／キャラクターデザイン:堀井久美／美術監督:Scott MacDonald／色彩設計:山本未有／撮影監督:横山翼／編集:木村祥明／音響監督:えびなやすのり／音響効果:川田清貴／音響制作:ダックスプロダクション／音楽:坂部剛／音楽制作:MAGES.／アニメーション制作:株式会社studio A-CAT／製作:わしかわいい製作委員会\n\n©2021 りゅうせんひろつぐ・藤ちょこ／マイクロマガジン社／わしかわいい製作委員会\n\n次話→so39913173","tags":["アニメ","第一話","異世界転生","転移","VR","小説家になろう","2022年冬アニメ","賢者の弟子を名乗る賢者","17:04から本編","わし、かわいい"],"cours":null,"colKey":"か","relatedSeries":[{"seriesId":289439,"title":"怪人開発部の黒井津さん","thumbnailUrl":null},{"seriesId":289442,"title":"幻想三國誌　天元霊心記","thumbnailUrl":null},{"seriesId":290424,"title":"HEROES(ヒーローズ)～Legend of Battle Disks～","thumbnailUrl":null},{"seriesId":290731,"title":"オンエアできない！","thumbnailUrl":null},{"seriesId":290733,"title":"失格紋の最強賢者","thumbnailUrl":null},{"seriesId":291244,"title":"プリンセスコネクト！Re:Dive season 2","thumbnailUrl":null},{"seriesId":292622,"title":"ガル学。Ⅱ～Lucky Stars～","thumbnailUrl":null},{"seriesId":309946,"title":"爆丸エボリューションズ","thumbnailUrl":null}],"episodes":[{"contentId":"so39883809","episodeNo":1,"title":"賢者の弟子を名乗る賢者　第1話　わし、かわいい……","viewCounter":39243,"startTime":"2022-01-12T00:00:00+09:00","thumbnailUrl":"https://nicovideo.cdn.nimg.jp/thumbnails/39883809/39883809.50470136"},{"contentId":"so39913173","episodeNo":2,"title":"賢者の弟子を名乗る賢者　第2話　わし、ウソついた……","viewCounter":25188,"startTime":"2022-01-19T00:00:00+09:00","thumbnailUrl":"https://nicovideo.cdn.nimg.jp/thumbnails/39913173/39913173.22930518"},{"contentId":"so39943827","episodeNo":3,"title":"賢者の弟子を名乗る賢者　第3話　わし……こういうのに弱いんじゃよなぁ","viewCounter":19296,"startTime":"2022-01-26T00:00:00+09:00","thumbnailUrl":"https://nicovideo.cdn.nimg.jp/thumbnails/39943827/39943827.31331411"},{"contentId":"so39976621","episodeNo":4,"title":"賢者の弟子を名乗る賢者　第4話　わし、もう限界！","viewCounter":17812,"startTime":"2022-02-02T00:00:00+09:00","thumbnailUrl":"https://nicovideo.cdn.nimg.jp/thumbnails/39976621/39976621.54377613"},{"contentId":"so40010269","episodeNo":5,"title":"賢者の弟子を名乗る賢者　第5話　わし、再・誕！","viewCounter":16267,"startTime":"2022-02-09T00:00:00+09:00","thumbnailUrl":"https://nicovideo.cdn.nimg.jp/thumbnails/40010269/40010269.23784385"},{"contentId":"so40045555","episodeNo":6,"title":"賢者の弟子を名乗る賢者　第6話　わし、着せ替えっ！","viewCounter":14185,"startTime":"2022-02-16T00:00:00+09:00","thumbnailUrl":"https://nicovideo.cdn.nimg.jp/thumbnails/40045555/40045555.46775475"},{"contentId":"so40078856","episodeNo":7,"title":"賢者の弟子を名乗る賢者　第7話　わし、最強！","viewCounter":14108,"startTime":"2022-02-23T00:00:00+09:00","thumbnailUrl":"https://nicovideo.cdn.nimg.jp/thumbnails/40078856/40078856.56898308"},{"contentId":"so40113011","episodeNo":8,"title":"賢者の弟子を名乗る賢者　第8話　わし、ダンブルフ","viewCounter":12660,"startTime":"2022-03-02T00:00:00+09:00","thumbnailUrl":"https://nicovideo.cdn.nimg.jp/thumbnails/40113011/40113011.93777338"},{"contentId":"so40146162","episodeNo":9,"title":"賢者の弟子を名乗る賢者　第9話　わし、こういう展開嫌いではないのぅ","viewCounter":11778,"startTime":"2022-03-09T00:00:00+09:00","thumbnailUrl":"https://nicovideo.cdn.nimg.jp/thumbnails/40146162/40146162.74715968"},{"contentId":"so40177953","episodeNo":10,"title":"賢者の弟子を名乗る賢者　第10話　わしっ、全裸っ！","viewCounter":11255,"startTime":"2022-03-16T00:00:00+09:00","thumbnailUrl":"https://nicovideo.cdn.nimg.jp/thumbnails/40177953/40177953.76007092"},{"contentId":"so40210496","episodeNo":11,"title":"賢者の弟子を名乗る賢者　第11話　わし……褒められてなくないか？","viewCounter":10883,"startTime":"2022-03-23T00:00:00+09:00","thumbnailUrl":"https://nicovideo.cdn.nimg.jp/thumbnails/40210496/40210496.78880914"},{"contentId":"so40242940","episodeNo":12,"title":"賢者の弟子を名乗る賢者　第12話　わし、参上！","viewCounter":9990,"startTime":"2022-03-30T00:00:00+09:00","thumbnailUrl":"https://nicovideo.cdn.nimg.jp/thumbnails/40242940/40242940.78719134"}]}