{"lastUpdated":"2026-06-16T19:53:22.776Z","seriesId":499245,"title":"賭ケグルイ××","thumbnailUrl":"https://nicovideo.cdn.nimg.jp/thumbnails/44465829/44465829.38537119","descriptionFirst":"ギャンブルの強さが絶対的基準とされる私立百花王学園。その一室で、蛇喰夢子、生志摩妄、そして拷問を家業とする蟲喰家の息女・蟲喰恵利美の３人によって、一歩間違えると自らの“指”を失うギャンブル『指切りギロチン』が行われていた。時を遡る事数日前、会長の桃喰綺羅莉は生徒会役員たちを招集する―。\n\n蛇喰夢子:早見沙織／早乙女芽亜里:田中美海／鈴井涼太:徳武竜也／皇 伊月:若井友希／西洞院百合子:奈波果林／生志摩 妄:伊瀬茉莉也／夢見弖ユメミ:芹澤 優／豆生田 楓:杉田智和／黄泉月るな:鵜殿麻由／五十嵐清華:福原綾香／桃喰綺羅莉・桃喰リリカ:沢城みゆき／等々喰定楽乃:潘 めぐみ／等々喰ユミ:井上遥乃／蟲喰恵利美:竹達彩奈／陰喰三欲:内山夕実／陽喰三理:大久保瑠美／和楽喰淑光:高垣彩陽／狛喰 希:北原沙弥香／骨喰ミラスラーヴァ:斎賀みつき／尾喰 茨:細谷佳正／尾喰 凜:石田 彰／×喰 零:朴 璐美\n\n原作:河本ほむら・尚村 透／監督:林 祐一郎・松田 清／シリーズ構成:小林靖子／キャラクターデザイン:秋田 学／美術監督:松田春香／色彩設計:末永絢子／CGディレクター:奥納 基／撮影監督:柳田貴志／編集:武宮むつみ／音響監督:藤田亜紀子／音響制作:HALF H・P STUDIO／音楽:TECHNOBOYS PULCRAFT GREEN-FUND／制作:MAPPA\n\n©河本ほむら・尚村透／SQUARE ENIX・「賭ケグルイ××」製作委員会\n\n次話→so44465839","tags":["アニメ","第一話","ガンガン・ヤングガンガン","2019年冬アニメ","NETFLIX解禁","賭ケグルイ1期→2期移動用","ホラー/サスペンス/推理"],"cours":"2019-冬","colKey":"か","relatedSeries":[],"episodes":[{"contentId":"so44465840","episodeNo":1,"title":"賭ケグルイ××　＜第1話＞　再ビ賭ケ狂ウ女タチ","viewCounter":5797,"startTime":"2025-01-01T00:00:00+09:00","thumbnailUrl":"https://nicovideo.cdn.nimg.jp/thumbnails/44465840/44465840.81585738"},{"contentId":"so44465839","episodeNo":2,"title":"賭ケグルイ××　＜第2話＞　百喰一族の女たち","viewCounter":2562,"startTime":"2025-01-01T00:00:00+09:00","thumbnailUrl":"https://nicovideo.cdn.nimg.jp/thumbnails/44465839/44465839.56592005"},{"contentId":"so44465838","episodeNo":3,"title":"賭ケグルイ××　＜第3話＞　この女触れるべからず","viewCounter":2237,"startTime":"2025-01-01T00:00:00+09:00","thumbnailUrl":"https://nicovideo.cdn.nimg.jp/thumbnails/44465838/44465838.55314970"},{"contentId":"so44465837","episodeNo":4,"title":"賭ケグルイ××　＜第4話＞　通じる女たち","viewCounter":2205,"startTime":"2025-01-01T00:00:00+09:00","thumbnailUrl":"https://nicovideo.cdn.nimg.jp/thumbnails/44465837/44465837.83216274"},{"contentId":"so44465836","episodeNo":5,"title":"賭ケグルイ××　＜第5話＞　かわる女","viewCounter":2069,"startTime":"2025-01-01T00:00:00+09:00","thumbnailUrl":"https://nicovideo.cdn.nimg.jp/thumbnails/44465836/44465836.98741274"},{"contentId":"so44465835","episodeNo":6,"title":"賭ケグルイ××　＜第6話＞　ハリウッドスターの女","viewCounter":2046,"startTime":"2025-01-01T00:00:00+09:00","thumbnailUrl":"https://nicovideo.cdn.nimg.jp/thumbnails/44465835/44465835.27101392"},{"contentId":"so44465834","episodeNo":7,"title":"賭ケグルイ××　＜第7話＞　裏切りの女","viewCounter":1920,"startTime":"2025-01-01T00:00:00+09:00","thumbnailUrl":"https://nicovideo.cdn.nimg.jp/thumbnails/44465834/44465834.56694334"},{"contentId":"so44465833","episodeNo":8,"title":"賭ケグルイ××　＜第8話＞　負けない女","viewCounter":1857,"startTime":"2025-01-01T00:00:00+09:00","thumbnailUrl":"https://nicovideo.cdn.nimg.jp/thumbnails/44465833/44465833.22544884"},{"contentId":"so44465832","episodeNo":9,"title":"賭ケグルイ××　＜第9話＞　傍の女","viewCounter":1817,"startTime":"2025-01-01T00:00:00+09:00","thumbnailUrl":"https://nicovideo.cdn.nimg.jp/thumbnails/44465832/44465832.6451190"},{"contentId":"so44465831","episodeNo":10,"title":"賭ケグルイ××　＜第10話＞　理の女","viewCounter":1860,"startTime":"2025-01-01T00:00:00+09:00","thumbnailUrl":"https://nicovideo.cdn.nimg.jp/thumbnails/44465831/44465831.63895952"},{"contentId":"so44465830","episodeNo":11,"title":"賭ケグルイ××　＜第11話＞　×を背負う女","viewCounter":1721,"startTime":"2025-01-01T00:00:00+09:00","thumbnailUrl":"https://nicovideo.cdn.nimg.jp/thumbnails/44465830/44465830.67109249"},{"contentId":"so44465829","episodeNo":12,"title":"賭ケグルイ××　＜第12話＞　零の女","viewCounter":1854,"startTime":"2025-01-01T00:00:00+09:00","thumbnailUrl":"https://nicovideo.cdn.nimg.jp/thumbnails/44465829/44465829.38537119"}]}