{"lastUpdated":"2026-06-16T23:53:34.324Z","seriesId":62864,"title":"ゾンビランドサガ","thumbnailUrl":"https://nicovideo.cdn.nimg.jp/thumbnails/33963154/33963154.74188571","descriptionFirst":"その生きる屍は、ある洋館でひっそりと目覚めた。それはただ、自分が誰かも、その場所がどこかも、何もわからぬまま、徘徊するのみ。やがて生きる屍は、恐るべき現実を目の当たりにし、自らの運命を告げられる。偽りの仮面をかぶり、闇の中を歩き続けるしかないのだと。そして、生きる屍に天からの光が差した時、人々は聞くだろう。狂乱の中に響き渡る叫びを。その、破滅の叫びを。―――――《巽幸太郎》の日記より\n\n巽 幸太郎:宮野 真守／源 さくら:本渡 楓／二階堂 サキ:田野 アサミ／水野 愛:種田 梨沙／紺野 純子:河瀬 茉希／ゆうぎり:衣川 里佳／星川 リリィ:田中 美海／山田 たえ:三石 琴乃／警察官Ａ:吉野 裕行／ロメロ:高戸 靖広\n\n原作:広報広聴課ゾンビ係／監督:境 宗久／シリーズ構成:村越 繋／キャラクターデザイン:深川 可純／美術監督:小倉 一男／撮影監督:柳田 貴志／色彩設計:佐々木 梓／編集:後藤 正浩／音楽:高梨 康治／音楽制作:エイベックス・ピクチャーズ／音響監督:境 宗久／音響制作:dugout／アニメーション制作:MAPPA\n\n©ゾンビランドサガ製作委員会\n\n次話→so33963153","tags":["アイドル","オリジナル(原作なし)アニメ","ご当地アニメ","MAPPA","2018年秋アニメ","サイゲオリジナル","佐賀"],"cours":"2018-秋","colKey":"さ","relatedSeries":[],"episodes":[{"contentId":"so33963154","episodeNo":1,"title":"ゾンビランドサガ　第1話　グッドモーニング SAGA","viewCounter":106395,"commentCounter":2548,"mylistCounter":1773,"lengthSeconds":1420,"startTime":"2018-10-07T22:00:00+09:00","thumbnailUrl":"https://nicovideo.cdn.nimg.jp/thumbnails/33963154/33963154.74188571"},{"contentId":"so33963153","episodeNo":2,"title":"ゾンビランドサガ　第2話　I♡HIPHOP SAGA","viewCounter":120409,"commentCounter":2937,"mylistCounter":372,"lengthSeconds":1419,"startTime":"2018-10-14T22:00:00+09:00","thumbnailUrl":"https://nicovideo.cdn.nimg.jp/thumbnails/33963153/33963153.65668513"},{"contentId":"so34021951","episodeNo":3,"title":"ゾンビランドサガ　第3話　DEAD OR LIVE SAGA","viewCounter":93819,"commentCounter":2306,"mylistCounter":250,"lengthSeconds":1420,"startTime":"2018-10-21T22:00:00+09:00","thumbnailUrl":"https://nicovideo.cdn.nimg.jp/thumbnails/34021951/34021951.28669147"},{"contentId":"so34063184","episodeNo":4,"title":"ゾンビランドサガ　第4話　ウォーミング・デッド SAGA","viewCounter":92631,"commentCounter":2129,"mylistCounter":239,"lengthSeconds":1420,"startTime":"2018-10-28T22:00:00+09:00","thumbnailUrl":"https://nicovideo.cdn.nimg.jp/thumbnails/34063184/34063184.70927151"},{"contentId":"so34063185","episodeNo":5,"title":"ゾンビランドサガ　第5話　君の心にナイスバード SAGA","viewCounter":102416,"commentCounter":2857,"mylistCounter":292,"lengthSeconds":1420,"startTime":"2018-11-04T22:00:00+09:00","thumbnailUrl":"https://nicovideo.cdn.nimg.jp/thumbnails/34063185/34063185.89234001"},{"contentId":"so34111780","episodeNo":6,"title":"ゾンビランドサガ　第6話　だってセンチメンタル SAGA","viewCounter":86483,"commentCounter":1793,"mylistCounter":216,"lengthSeconds":1420,"startTime":"2018-11-11T22:00:00+09:00","thumbnailUrl":"https://nicovideo.cdn.nimg.jp/thumbnails/34111780/34111780.47198116"},{"contentId":"so34170749","episodeNo":7,"title":"ゾンビランドサガ　第7話　けれどゾンビメンタル SAGA","viewCounter":108947,"commentCounter":2994,"mylistCounter":362,"lengthSeconds":1420,"startTime":"2018-11-18T22:00:00+09:00","thumbnailUrl":"https://nicovideo.cdn.nimg.jp/thumbnails/34170749/34170749.30138420"},{"contentId":"so34209027","episodeNo":8,"title":"ゾンビランドサガ　第8話　GOGO ネバーランド SAGA","viewCounter":100536,"commentCounter":3088,"mylistCounter":336,"lengthSeconds":1420,"startTime":"2018-11-25T22:00:00+09:00","thumbnailUrl":"https://nicovideo.cdn.nimg.jp/thumbnails/34209027/34209027.24043435"},{"contentId":"so34243602","episodeNo":9,"title":"ゾンビランドサガ　第9話　一度は尽きたこの命 なんの因果か蘇り 歌い踊るが宿命（さだめ）なら 親友（とも）への想いを胸に秘め 貫くまでよ己の SAGA","viewCounter":79604,"commentCounter":2191,"mylistCounter":253,"lengthSeconds":1420,"startTime":"2018-12-02T22:00:00+09:00","thumbnailUrl":"https://nicovideo.cdn.nimg.jp/thumbnails/34243602/34243602.1738938"},{"contentId":"so34273104","episodeNo":10,"title":"ゾンビランドサガ　第10話　NO ZOMBIE NO IDOL SAGA","viewCounter":65150,"commentCounter":1380,"mylistCounter":205,"lengthSeconds":1420,"startTime":"2018-12-09T22:00:00+09:00","thumbnailUrl":"https://nicovideo.cdn.nimg.jp/thumbnails/34273104/34273104.73201611"},{"contentId":"so34316208","episodeNo":11,"title":"ゾンビランドサガ　第11話　世界にひとつだけの SAGA","viewCounter":67210,"commentCounter":1346,"mylistCounter":219,"lengthSeconds":1420,"startTime":"2018-12-16T22:00:00+09:00","thumbnailUrl":"https://nicovideo.cdn.nimg.jp/thumbnails/34316208/34316208.97289121"},{"contentId":"so34349745","episodeNo":12,"title":"ゾンビランドサガ　第12話　グッドモーニング アゲイン SAGA","viewCounter":90099,"commentCounter":2207,"mylistCounter":339,"lengthSeconds":1420,"startTime":"2018-12-23T22:00:00+09:00","thumbnailUrl":"https://nicovideo.cdn.nimg.jp/thumbnails/34349745/34349745.42459426"}]}