{"lastUpdated":"2026-06-16T18:19:18.954Z","seriesId":62985,"title":"咲-Saki-","thumbnailUrl":"https://nicovideo.cdn.nimg.jp/thumbnails/32367406/32367406.42837341","descriptionFirst":"訳も分からず麻雀部に連れて行かれ、麻雀を打つ事になった咲。そこには小川のほとりで出会った少女、和がいた。結果、対局は和の勝利で終わったが、咲の打ち方に疑問を感じた和は、もう一回打って欲しいと願う。\n\n宮永 咲(みやなが さき) CV: 植田 佳奈／ 原村 和(はらむら のどか)CV: 小清水 亜美／ 片岡 優希(かたおか ゆうき)CV: 釘宮 理恵／ 染谷 まこ(そめや まこ)CV: 白石 涼子／ 竹井 久(たけい ひさ) CV: 伊藤 静／ 須賀 京太郎(すが きょうたろう) CV: 福山 潤\n\n原作:小林 立 (掲載｢ヤングガンガン｣スクウェア・エニックス刊)／監督:小野 学／助監督:セトウケンジ／シリーズ構成・脚本:浦畑達彦／キャラクターデザイン&総作画監督:佐々木 政勝／美術監督・設定:松本 浩樹<スタジオ・イースター>／編集:三嶋章紀／色彩設計:内林裕美／撮影監督:林コージロー／3D制作:サンジゲン／音響監督:鶴岡陽太<楽音舎>／アニメーション制作:GONZO<第5スタジオ>／音楽製作:ランティス\n\n©小林 立/スクウェアエニックス・清澄高校麻雀部\n\n次話→so32367439","tags":["アニメ","第一話","スポーツ","競技","2009年春アニメ","ガンガン・ヤングガンガン","咲-SAKI-_第一話リンク","麻雀","咲-SAKI-","人間やめましたシリーズ","はいてない"],"cours":null,"colKey":"さ","relatedSeries":[],"episodes":[{"contentId":"so32367406","episodeNo":1,"title":"咲-Saki-　第1話　出会い","viewCounter":53310,"startTime":"2018-10-12T10:00:00+09:00","thumbnailUrl":"https://nicovideo.cdn.nimg.jp/thumbnails/32367406/32367406.42837341"},{"contentId":"so32367439","episodeNo":2,"title":"咲-Saki-　第2話　勝負","viewCounter":38054,"startTime":"2018-10-12T10:00:00+09:00","thumbnailUrl":"https://nicovideo.cdn.nimg.jp/thumbnails/32367439/32367439.59541718"},{"contentId":"so32367484","episodeNo":3,"title":"咲-Saki-　第3話　対立","viewCounter":29325,"startTime":"2018-10-12T10:00:00+09:00","thumbnailUrl":"https://nicovideo.cdn.nimg.jp/thumbnails/32367484/32367484.32097307"},{"contentId":"so32367485","episodeNo":4,"title":"咲-Saki-　第4話　翻弄","viewCounter":26360,"startTime":"2018-10-12T10:00:00+09:00","thumbnailUrl":"https://nicovideo.cdn.nimg.jp/thumbnails/32367485/32367485.39267618"},{"contentId":"so32367499","episodeNo":5,"title":"咲-Saki-　第5話　合宿","viewCounter":26606,"startTime":"2018-10-12T10:00:00+09:00","thumbnailUrl":"https://nicovideo.cdn.nimg.jp/thumbnails/32367499/32367499.43835767"},{"contentId":"so32367500","episodeNo":6,"title":"咲-Saki-　第6話　開幕","viewCounter":26790,"startTime":"2018-10-12T10:00:00+09:00","thumbnailUrl":"https://nicovideo.cdn.nimg.jp/thumbnails/32367500/32367500.27845759"},{"contentId":"so32367501","episodeNo":7,"title":"咲-Saki-　第7話　伝統","viewCounter":27909,"startTime":"2018-10-12T10:00:00+09:00","thumbnailUrl":"https://nicovideo.cdn.nimg.jp/thumbnails/32367501/32367501.34346925"},{"contentId":"so32367447","episodeNo":8,"title":"咲-Saki-　第8話　前夜","viewCounter":24991,"startTime":"2018-10-12T10:00:00+09:00","thumbnailUrl":"https://nicovideo.cdn.nimg.jp/thumbnails/32367447/32367447.33492302"},{"contentId":"so32367446","episodeNo":9,"title":"咲-Saki-　第9話　開眼","viewCounter":25708,"startTime":"2018-10-12T10:00:00+09:00","thumbnailUrl":"https://nicovideo.cdn.nimg.jp/thumbnails/32367446/32367446.44297326"},{"contentId":"so32367445","episodeNo":10,"title":"咲-Saki-　第10話　初心者","viewCounter":25463,"startTime":"2018-10-12T10:00:00+09:00","thumbnailUrl":"https://nicovideo.cdn.nimg.jp/thumbnails/32367445/32367445.50810835"},{"contentId":"so32367444","episodeNo":11,"title":"咲-Saki-　第11話　悪戯","viewCounter":26843,"startTime":"2018-10-12T10:00:00+09:00","thumbnailUrl":"https://nicovideo.cdn.nimg.jp/thumbnails/32367444/32367444.26528511"},{"contentId":"so32367443","episodeNo":12,"title":"咲-Saki-　第12話　目醒め","viewCounter":26575,"startTime":"2018-10-12T10:00:00+09:00","thumbnailUrl":"https://nicovideo.cdn.nimg.jp/thumbnails/32367443/32367443.59322576"},{"contentId":"so32367442","episodeNo":13,"title":"咲-Saki-　第13話　微熱","viewCounter":24762,"startTime":"2018-10-12T10:00:00+09:00","thumbnailUrl":"https://nicovideo.cdn.nimg.jp/thumbnails/32367442/32367442.40448253"},{"contentId":"so32367441","episodeNo":14,"title":"咲-Saki-　第14話　存在","viewCounter":25059,"startTime":"2018-10-12T10:00:00+09:00","thumbnailUrl":"https://nicovideo.cdn.nimg.jp/thumbnails/32367441/32367441.75909867"},{"contentId":"so32367440","episodeNo":15,"title":"咲-Saki-　第15話　魔物","viewCounter":31145,"startTime":"2018-10-12T10:00:00+09:00","thumbnailUrl":"https://nicovideo.cdn.nimg.jp/thumbnails/32367440/32367440.23178121"},{"contentId":"so32367419","episodeNo":16,"title":"咲-Saki-　第16話　結託","viewCounter":29790,"startTime":"2018-10-12T10:00:00+09:00","thumbnailUrl":"https://nicovideo.cdn.nimg.jp/thumbnails/32367419/32367419.71474336"},{"contentId":"so32367407","episodeNo":17,"title":"咲-Saki-　第17話　悪夢","viewCounter":30955,"startTime":"2018-10-12T10:00:00+09:00","thumbnailUrl":"https://nicovideo.cdn.nimg.jp/thumbnails/32367407/32367407.62005940"},{"contentId":"so32367408","episodeNo":18,"title":"咲-Saki-　第18話　繋がり","viewCounter":38071,"startTime":"2018-10-12T10:00:00+09:00","thumbnailUrl":"https://nicovideo.cdn.nimg.jp/thumbnails/32367408/32367408.65572427"},{"contentId":"so32367409","episodeNo":19,"title":"咲-Saki-　第19話　友達","viewCounter":40367,"startTime":"2018-10-12T10:00:00+09:00","thumbnailUrl":"https://nicovideo.cdn.nimg.jp/thumbnails/32367409/32367409.34529676"},{"contentId":"so32367410","episodeNo":20,"title":"咲-Saki-　第20話　姉妹","viewCounter":24821,"startTime":"2018-10-12T10:00:00+09:00","thumbnailUrl":"https://nicovideo.cdn.nimg.jp/thumbnails/32367410/32367410.70845391"},{"contentId":"so32367411","episodeNo":21,"title":"咲-Saki-　第21話　追想","viewCounter":22927,"startTime":"2018-10-12T10:00:00+09:00","thumbnailUrl":"https://nicovideo.cdn.nimg.jp/thumbnails/32367411/32367411.78221166"},{"contentId":"so32367412","episodeNo":22,"title":"咲-Saki-　第22話　約束","viewCounter":21329,"startTime":"2018-10-12T10:00:00+09:00","thumbnailUrl":"https://nicovideo.cdn.nimg.jp/thumbnails/32367412/32367412.7778121"},{"contentId":"so32367413","episodeNo":23,"title":"咲-Saki-　第23話　本気","viewCounter":23668,"startTime":"2018-10-12T10:00:00+09:00","thumbnailUrl":"https://nicovideo.cdn.nimg.jp/thumbnails/32367413/32367413.10504937"},{"contentId":"so32367414","episodeNo":24,"title":"咲-Saki-　第24話　夏祭り","viewCounter":19614,"startTime":"2018-10-12T10:00:00+09:00","thumbnailUrl":"https://nicovideo.cdn.nimg.jp/thumbnails/32367414/32367414.3320267"},{"contentId":"so32367415","episodeNo":25,"title":"咲-Saki-　第25話　全国","viewCounter":23019,"startTime":"2018-10-12T10:00:00+09:00","thumbnailUrl":"https://nicovideo.cdn.nimg.jp/thumbnails/32367415/32367415.75285381"}]}