{"lastUpdated":"2026-06-16T12:18:21.074Z","seriesId":96334,"title":"ハッピージョージ","thumbnailUrl":"https://nicovideo.cdn.nimg.jp/thumbnails/32224508/32224508.44706876","descriptionFirst":"ボッチ、ブレッド・テール:ケイト・アロー／ロバート・テール:今野幸平／イーディー・テール:森由果／ポニー・テール:ニーコ／肉巻オニギリ:平山笑美／上戸エンピツ:宮本琴未／上戸ペン:長谷川 歩美／アンダルシア、アンディ・テール:安田梓司／エドガー:谷口洋一／肉巻ライス:柳橋なつみ\n\n監督・原作・脚本:ケイト・アロー／プロデューサー:福井政文／主題歌:リサメロディー\n\n次話→so32224509","tags":["アニメ","第一話","コメディ","ギャグ","ショートアニメ","2015年春アニメ","ハッピージョージ"],"cours":null,"colKey":"は","relatedSeries":[{"seriesId":96171,"title":"ガンスリンガー ストラトス","thumbnailUrl":"https://nicovideo.cdn.nimg.jp/thumbnails/32212475/32212475.78552575"},{"seriesId":96177,"title":"ハイスクールD×D BorN","thumbnailUrl":"https://nicovideo.cdn.nimg.jp/thumbnails/31946152/31946152.72174375"},{"seriesId":96179,"title":"俺物語!!","thumbnailUrl":"https://nicovideo.cdn.nimg.jp/thumbnails/31946221/31946221.16930143"},{"seriesId":96186,"title":"ミカグラ学園組曲","thumbnailUrl":"https://nicovideo.cdn.nimg.jp/thumbnails/32019358/32019358.59946931"},{"seriesId":96559,"title":"ピカイア！","thumbnailUrl":"https://nicovideo.cdn.nimg.jp/thumbnails/31997353/31997353.57155814"},{"seriesId":96618,"title":"秘密結社 鷹の爪DO","thumbnailUrl":"https://nicovideo.cdn.nimg.jp/thumbnails/32000487/32000487.61640757"},{"seriesId":495836,"title":"終わりのセラフ","thumbnailUrl":"https://nicovideo.cdn.nimg.jp/thumbnails/44367126/44367126.41348320"},{"seriesId":498115,"title":"英国一家、日本を食べる","thumbnailUrl":"https://nicovideo.cdn.nimg.jp/thumbnails/44434212/44434212.38955967"}],"episodes":[{"contentId":"so32224508","episodeNo":1,"title":"ハッピージョージ　#1～#10　テール家の新生活／ぼくコアラのボッチ／おとなりさん／ポニーの手作りクッキング／アンダルシアは天才犬？／ごはんの時間／アンディ・テールの計画／私をパグと呼ばないで／スクールバス／ロブは転校生","viewCounter":241,"startTime":"2015-10-16T10:00:00+09:00","thumbnailUrl":"https://nicovideo.cdn.nimg.jp/thumbnails/32224508/32224508.44706876"},{"contentId":"so32224509","episodeNo":2,"title":"ハッピージョージ　#11～#20　カルチャーショック／居眠り／サラとブレッド／かくれんぼ／それぞれの思い／お風呂の時間／エドガーの苦労／眠れぬ夜／ロブの名案／ペンの告白","viewCounter":38,"startTime":"2015-10-16T10:00:00+09:00","thumbnailUrl":"https://nicovideo.cdn.nimg.jp/thumbnails/32224509/32224509.35559490"},{"contentId":"so32224510","episodeNo":3,"title":"ハッピージョージ　#21～#30　ドローン大作戦／イーディのSNS／なんだかアメリカン？／アーティストの悩み／リサメロディーへの質問／バーでのひととき／アンダルシアの恋／テール家フリーズ／眠れぬ夜 パート2／小顔になりたい","viewCounter":34,"startTime":"2015-11-06T10:00:00+09:00","thumbnailUrl":"https://nicovideo.cdn.nimg.jp/thumbnails/32224510/32224510.97243169"},{"contentId":"so32224511","episodeNo":4,"title":"ハッピージョージ　#31～#41　めざせ！人気動画投稿者！／恐怖のお医者さんごっこ／アンディとブレッドの関係／ボッチの英語レッスン／アンダルシアの意識／ふたりの疑念／イーディのイライラ／ペンの気持ち／フードの中身／バーでのひととき　パート2／ブレッドのタイムスリップ","viewCounter":46,"startTime":"2016-01-29T10:00:00+09:00","thumbnailUrl":"https://nicovideo.cdn.nimg.jp/thumbnails/32224511/32224511.87091592"},{"contentId":"so32224512","episodeNo":5,"title":"ハッピージョージ　#42～#52　金縛りの夜／ロブのダイエット／電車にて／恐怖のかくれんぼ／ニューヨークへ／ロールプレイング／理想と現実／カピバラ町長／神様と宇宙人／ボッチの異変／ねがいごと","viewCounter":35,"startTime":"2016-04-08T10:00:00+09:00","thumbnailUrl":"https://nicovideo.cdn.nimg.jp/thumbnails/32224512/32224512.19332666"}]}