{"lastUpdated":"2026-06-16T19:53:22.776Z","seriesId":96572,"title":"SUPER LOVERS 2","thumbnailUrl":"https://nicovideo.cdn.nimg.jp/thumbnails/32000157/32000157.64821892","descriptionFirst":"兄弟4人一つ屋根の下で暮らすという長男・晴の夢が叶って、三ヶ月。だが、春子が｢零をスイスに連れて帰る｣と言いだしたせいで、海棠家は一気に嵐に。幹子から春子の秘めた寂しさを聞いた零は、それでも晴に求められる限り日本にいたいと願う。そんな言葉にできない想いを抱えたまま｢ただの弟｣であろうとする零だったが……。\n\n海棠零:皆川純子／海棠晴:前野智昭／海棠亜樹:松岡禎丞／海棠蒔麻:寺島拓篤／佐々木郁芳:村瀬歩／黒崎十全:福島潤／春子・D・ディークマン:田中敦子／柏木幹子:沢海陽子／近藤紀里:白石涼子／清華:斎賀みつき／篁志朗:置鮎龍太郎／斯波夏生:佐藤拓也\n\n原作:あべ美幸（株式会社KADOKAWA／「エメラルド」連載）／監督:石平信司／シリーズ構成:中村能子／キャラクターデザイン:瀧原美樹／助監督:渡部穏寛／美術監督:三宅昌和／色彩設計:桂木今里／撮影監督:越山麻彦／編集:松村正宏／音響監督:はたしょう二／音響効果:出雲範子／録音:八巻大樹／音響制作:ダックスプロダクション／音楽:高梨康治＆片山修志＆加藤賢二（Team-MAX)／音楽制作:日本コロムビア／アニメーション制作:スタジオディーン／製作:「SUPER LOVERS 2」製作委員会／オープニング・テーマ:「晴レ色メロディー」矢田悠祐／エンディング・テーマ:「ギュンとラブソング」海棠4兄弟　海棠零(CV：皆川純子)、海棠晴(CV：前野智昭)、海棠亜樹(CV：松岡禎丞)、海棠蒔麻(CV：寺島拓篤)\n\n次話→so32000158","tags":["アニメ","第一話","スタジオディーン","2017年冬アニメ","ED:レン＆ハル","恋愛/ラブコメ","BL/ボーイズラブ"],"cours":"2017-冬","colKey":"さ","relatedSeries":[],"episodes":[{"contentId":"so32000157","episodeNo":1,"title":"SUPER LOVERS 2　#1　｢in the pink｣","viewCounter":2012,"startTime":"2017-01-17T12:00:00+09:00","thumbnailUrl":"https://nicovideo.cdn.nimg.jp/thumbnails/32000157/32000157.64821892"},{"contentId":"so32000158","episodeNo":2,"title":"SUPER LOVERS 2　#2　｢gold star｣","viewCounter":1972,"startTime":"2017-01-24T12:00:00+09:00","thumbnailUrl":"https://nicovideo.cdn.nimg.jp/thumbnails/32000158/32000158.97816574"},{"contentId":"so32000159","episodeNo":3,"title":"SUPER LOVERS 2　#3　｢white lie｣","viewCounter":1686,"startTime":"2017-01-31T12:00:00+09:00","thumbnailUrl":"https://nicovideo.cdn.nimg.jp/thumbnails/32000159/32000159.92200043"},{"contentId":"so32000199","episodeNo":4,"title":"SUPER LOVERS 2　#4　｢see red｣","viewCounter":1713,"startTime":"2017-02-07T12:00:00+09:00","thumbnailUrl":"https://nicovideo.cdn.nimg.jp/thumbnails/32000199/32000199.67019037"},{"contentId":"so32000200","episodeNo":5,"title":"SUPER LOVERS 2　#5　｢black and white｣","viewCounter":1737,"startTime":"2017-02-14T12:00:00+09:00","thumbnailUrl":"https://nicovideo.cdn.nimg.jp/thumbnails/32000200/32000200.53844384"},{"contentId":"so32000201","episodeNo":6,"title":"SUPER LOVERS 2　#6　「marine blue」","viewCounter":1625,"startTime":"2017-02-21T12:00:00+09:00","thumbnailUrl":"https://nicovideo.cdn.nimg.jp/thumbnails/32000201/32000201.1430675"},{"contentId":"so32000202","episodeNo":7,"title":"SUPER LOVERS 2　#7　｢sweet peach｣","viewCounter":1557,"startTime":"2017-02-28T12:00:00+09:00","thumbnailUrl":"https://nicovideo.cdn.nimg.jp/thumbnails/32000202/32000202.12306532"},{"contentId":"so32000203","episodeNo":8,"title":"SUPER LOVERS 2　#8　｢heavy fog｣","viewCounter":1496,"startTime":"2017-03-07T12:00:00+09:00","thumbnailUrl":"https://nicovideo.cdn.nimg.jp/thumbnails/32000203/32000203.89183721"},{"contentId":"so32000204","episodeNo":9,"title":"SUPER LOVERS 2　#9　｢silver lining｣","viewCounter":1659,"startTime":"2017-03-14T12:00:00+09:00","thumbnailUrl":"https://nicovideo.cdn.nimg.jp/thumbnails/32000204/32000204.73186000"},{"contentId":"so32000205","episodeNo":10,"title":"SUPER LOVERS 2　#10　「happy days」","viewCounter":1733,"startTime":"2017-03-21T12:00:00+09:00","thumbnailUrl":"https://nicovideo.cdn.nimg.jp/thumbnails/32000205/32000205.15795457"}]}