{"seriesId":-1891177209,"title":"はじまりの冒険者たち～レジェンド・オブ・クリスタニア～","thumbnailUrl":"https://nicovideo.cdn.nimg.jp/thumbnails/31881850/31881850.47784102","descriptionFirst":"作家・水野良とグループSNEが構築した異世界フォーセリアの物語の内、大陸クリスタニアを舞台とした英雄譚が独立して劇場版アニメになったもの。■神獣たちが住まう外界から隔絶された大地・クリスタニア。謎の声に導かれるがままその地へと向かう青年・レードンの胸中に渦巻くのは、両親を暗殺した宰相たちへの復讐心。力を得るための旅を続ける彼はやがて、クリスタニアへと誘う声の主が邪神バルバスであることを知った。大切な仲間を連れ去っていった邪神を相手に初心を貫き屈するか、それとも抗うか……。決断を迫られたレードンの進むべき道とは。■剣と魔法の世界で獣人や妖精が躍動する、まさに王道のファンタジー映画。\n\n緑川 光:(レードン)／弥生 みつき:(アデリシア)／関 俊彦:(ナーセル)／立木 文彦:(クイルド)／西村 ちなみ:(ライファン)／矢尾 一樹:(オーヴィル)／玉川 紗己子:(ピロテース)／小林 清志:(バルバス)／神谷 明:(アシュラム)\n\n原作:水野 良／製作:角川 歴彦／企画:田宮 武／プロデューサー:横山 和夫／コーディネーター:高梨 由美子／脚本:遠藤 明範／監督:中村 隆太郎／音楽:大島 ミチル、佐橋 俊彦／キャラクター原案:宝谷 幸稔／神獣キャラクター原案:佐藤 肇／キャラクターデザイン・総作画監督:松田 勝巳／作画監督:清水 保行、水村 良男、宮沢 康紀／美術監督:大野 広司／色彩設計:大武 恭子／撮影監督:森下 成一／音響監督:三間 雅文／編集:瀬山 武司","tags":["SF/ファンタジー","アニメ映画","1995年公開アニメーション映画","クリスタニア","フォーセリア"],"cours":null,"colKey":"は","franchiseKey":null,"relatedSeries":[],"isAvailable":true,"firstSeen":"2012-12-28T10:00:00+09:00","lastSeen":"2012-12-28T10:00:00+09:00","lastSeenAt":null,"episodes":[{"contentId":"so31881850","episodeNo":null,"title":"はじまりの冒険者たち～レジェンド・オブ・クリスタニア～　はじまりの冒険者たち～レジェンド・オブ・クリスタニア～","viewCounter":5998,"commentCounter":61,"likeCounter":12,"mylistCounter":35,"lengthSeconds":4729,"startTime":"2012-12-28T10:00:00+09:00","thumbnailUrl":"https://nicovideo.cdn.nimg.jp/thumbnails/31881850/31881850.47784102","description":"作家・水野良とグループSNEが構築した異世界フォーセリアの物語の内、大陸クリスタニアを舞台とした英雄譚が独立して劇場版アニメになったもの。■神獣たちが住まう外界から隔絶された大地・クリスタニア。謎の声に導かれるがままその地へと向かう青年・レードンの胸中に渦巻くのは、両親を暗殺した宰相たちへの復讐心。力を得るための旅を続ける彼はやがて、クリスタニアへと誘う声の主が邪神バルバスであることを知った。大切な仲間を連れ去っていった邪神を相手に初心を貫き屈するか、それとも抗うか……。決断を迫られたレードンの進むべき道とは。■剣と魔法の世界で獣人や妖精が躍動する、まさに王道のファンタジー映画。\n\n緑川 光:(レードン)／弥生 みつき:(アデリシア)／関 俊彦:(ナーセル)／立木 文彦:(クイルド)／西村 ちなみ:(ライファン)／矢尾 一樹:(オーヴィル)／玉川 紗己子:(ピロテース)／小林 清志:(バルバス)／神谷 明:(アシュラム)\n\n原作:水野 良／製作:角川 歴彦／企画:田宮 武／プロデューサー:横山 和夫／コーディネーター:高梨 由美子／脚本:遠藤 明範／監督:中村 隆太郎／音楽:大島 ミチル、佐橋 俊彦／キャラクター原案:宝谷 幸稔／神獣キャラクター原案:佐藤 肇／キャラクターデザイン・総作画監督:松田 勝巳／作画監督:清水 保行、水村 良男、宮沢 康紀／美術監督:大野 広司／色彩設計:大武 恭子／撮影監督:森下 成一／音響監督:三間 雅文／編集:瀬山 武司","tags":["SF/ファンタジー","アニメ映画","1995年公開アニメーション映画","はじまりの冒険者たち","クリスタニア","フォーセリア"],"tagsCurated":["SF/ファンタジー","アニメ映画"],"lastUpdated":"2026-06-22T00:06:04.790Z"}]}