{"seriesId":67982,"title":"劇場版 黒子のバスケ LAST GAME","thumbnailUrl":"https://nicovideo.cdn.nimg.jp/thumbnails/43663334/43663334.14905835","descriptionFirst":"誠凛高校バスケ部に入部した黒子テツヤと火神大我。抜群のセンスを持つ火神に対し、黒子は誰もが驚くほど影が薄い存在だった。だが、黒子は強豪・帝光中学で「キセキの世代」と呼ばれた5人の天才と共に戦う“幻の6人目（シックスマン）”として活躍していた。“影”と“光”の名コンビとなった二人が主戦力となり、誠凛バスケ部はウインターカップ出場を果たす。そして「キセキの世代」との激戦の末、ついに全国制覇を成し遂げた。黒子たちは2年生となり、夏が終わるころ、アメリカから注目のストリートバスケットボールチーム「Jabberwock（ジャバウォック）」が来日した。しかし親善試合で彼らが見せたのは、圧倒的な実力で日本チームをねじ伏せ、日本のバスケを嘲笑う姿だった。その態度に激怒したリコの父・景虎は黒子と火神、そして「キセキの世代」を集め、Jabberwockにリベンジマッチを宣言する！ 今回限りの最強ドリームチーム「VORPAL SWORDS（ヴォーパル・ソーズ）」、ここに集結!!\n\n黒子テツヤ:小野賢章／火神大我:小野友樹／赤司征十郎:神谷浩史／青峰大輝:諏訪部順一／緑間真太郎:小野大輔／黄瀬涼太:木村良平／紫原 敦:鈴村健一／ナッシュ・ゴールド・Jr.:緑川 光／ジェイソン・シルバー:稲田 徹　他\n\n原作:藤巻忠俊（集英社 ジャンプ コミックス刊）／監督:多田俊介／脚本:高木 登／キャラクターデザイン:菊地洋子／総作画監督:後藤隆幸、菊地洋子／美術監督:鈴木路恵／色彩設計:竹田由香／撮影監督:荒井栄児／ CGIディレクター:磯部兼士／編集:植松淳一／音響監督:三間雅文／音楽:池 頼広／主題歌:「Glorious days」GRANRODEO／アニメーション制作:プロダクションI.G／配給:松竹／製作:劇場版「黒子のバスケ」製作委員会\n\n© 藤巻忠俊／集英社・劇場版「黒子のバスケ」製作委員会","tags":["黒子のバスケ","少年ジャンプ","アニメ映画","黒子のバスケ3期→劇場版(移動タグ)"],"cours":null,"colKey":"か","franchiseKey":null,"relatedSeries":[],"isAvailable":true,"firstSeen":"2024-05-01T00:00:00+09:00","lastSeen":"2024-05-01T00:00:00+09:00","lastSeenAt":"2026-06-24T23:43:42.876Z","episodes":[{"contentId":"so43663334","episodeNo":6,"title":"劇場版 黒子のバスケ LAST GAME　本編","viewCounter":6234,"commentCounter":444,"likeCounter":63,"mylistCounter":95,"lengthSeconds":5459,"startTime":"2024-05-01T00:00:00+09:00","thumbnailUrl":"https://nicovideo.cdn.nimg.jp/thumbnails/43663334/43663334.14905835","description":"誠凛高校バスケ部に入部した黒子テツヤと火神大我。抜群のセンスを持つ火神に対し、黒子は誰もが驚くほど影が薄い存在だった。だが、黒子は強豪・帝光中学で「キセキの世代」と呼ばれた5人の天才と共に戦う“幻の6人目（シックスマン）”として活躍していた。“影”と“光”の名コンビとなった二人が主戦力となり、誠凛バスケ部はウインターカップ出場を果たす。そして「キセキの世代」との激戦の末、ついに全国制覇を成し遂げた。黒子たちは2年生となり、夏が終わるころ、アメリカから注目のストリートバスケットボールチーム「Jabberwock（ジャバウォック）」が来日した。しかし親善試合で彼らが見せたのは、圧倒的な実力で日本チームをねじ伏せ、日本のバスケを嘲笑う姿だった。その態度に激怒したリコの父・景虎は黒子と火神、そして「キセキの世代」を集め、Jabberwockにリベンジマッチを宣言する！ 今回限りの最強ドリームチーム「VORPAL SWORDS（ヴォーパル・ソーズ）」、ここに集結!!\n\n黒子テツヤ:小野賢章／火神大我:小野友樹／赤司征十郎:神谷浩史／青峰大輝:諏訪部順一／緑間真太郎:小野大輔／黄瀬涼太:木村良平／紫原 敦:鈴村健一／ナッシュ・ゴールド・Jr.:緑川 光／ジェイソン・シルバー:稲田 徹　他\n\n原作:藤巻忠俊（集英社 ジャンプ コミックス刊）／監督:多田俊介／脚本:高木 登／キャラクターデザイン:菊地洋子／総作画監督:後藤隆幸、菊地洋子／美術監督:鈴木路恵／色彩設計:竹田由香／撮影監督:荒井栄児／ CGIディレクター:磯部兼士／編集:植松淳一／音響監督:三間雅文／音楽:池 頼広／主題歌:「Glorious days」GRANRODEO／アニメーション制作:プロダクションI.G／配給:松竹／製作:劇場版「黒子のバスケ」製作委員会\n\n© 藤巻忠俊／集英社・劇場版「黒子のバスケ」製作委員会","tags":["劇場版_黒子のバスケ_LAST_GAME","黒子のバスケ","少年ジャンプ","アニメ映画","黒子のバスケ3期→劇場版(移動タグ)"],"tagsCurated":["少年ジャンプ","アニメ映画"],"lastUpdated":"2026-06-25T00:00:56.382Z"}]}